<?xml version="1.0" encoding="us-ascii"?>
<MQSim_Results>
	<Host>
		<Host.IO_Flow>
				 <Name>Host.IO_Flow.Synth.No_0</Name>
				 <Request_Count>1027516</Request_Count>
				 <Read_Request_Count>0</Read_Request_Count>
				 <Write_Request_Count>1027516</Write_Request_Count>
				 <IOPS>10275.160000</IOPS>
				 <IOPS_Read>0.000000</IOPS_Read>
				 <IOPS_Write>10275.160000</IOPS_Write>
				 <Device_Response_Time>778</Device_Response_Time>
				 <Min_Device_Response_Time>3</Min_Device_Response_Time>
				 <Max_Device_Response_Time>107910</Max_Device_Response_Time>
				 <End_to_End_Request_Delay>778</End_to_End_Request_Delay>
				 <Min_End_to_End_Request_Delay>3</Min_End_to_End_Request_Delay>
				 <Max_End_to_End_Request_Delay>107910</Max_End_to_End_Request_Delay>
		</Host.IO_Flow>
		<Host.IO_Flow>
				 <Name>Host.IO_Flow.Synth.No_1</Name>
				 <Request_Count>1027842</Request_Count>
				 <Read_Request_Count>0</Read_Request_Count>
				 <Write_Request_Count>1027842</Write_Request_Count>
				 <IOPS>10278.420000</IOPS>
				 <IOPS_Read>0.000000</IOPS_Read>
				 <IOPS_Write>10278.420000</IOPS_Write>
				 <Device_Response_Time>12454</Device_Response_Time>
				 <Min_Device_Response_Time>3</Min_Device_Response_Time>
				 <Max_Device_Response_Time>138461</Max_Device_Response_Time>
				 <End_to_End_Request_Delay>12454</End_to_End_Request_Delay>
				 <Min_End_to_End_Request_Delay>3</Min_End_to_End_Request_Delay>
				 <Max_End_to_End_Request_Delay>138461</Max_End_to_End_Request_Delay>
		</Host.IO_Flow>
	</Host>
	<SSDDevice>
		<SSDDevice.HostInterface>
				 <Name>SSDDevice.HostInterface</Name>
			<SSDDevice.IO_Stream>
					 <Stream_ID>0</Stream_ID>
					 <Average_Read_Transaction_Turnaround_Time>0</Average_Read_Transaction_Turnaround_Time>
					 <Average_Read_Transaction_Execution_Time>0</Average_Read_Transaction_Execution_Time>
					 <Average_Read_Transaction_Transfer_Time>0</Average_Read_Transaction_Transfer_Time>
					 <Average_Read_Transaction_Waiting_Time>0</Average_Read_Transaction_Waiting_Time>
					 <Average_Write_Transaction_Turnaround_Time>2686</Average_Write_Transaction_Turnaround_Time>
					 <Average_Write_Transaction_Execution_Time>224</Average_Write_Transaction_Execution_Time>
					 <Average_Write_Transaction_Transfer_Time>3</Average_Write_Transaction_Transfer_Time>
					 <Average_Write_Transaction_Waiting_Time>2457</Average_Write_Transaction_Waiting_Time>
			</SSDDevice.IO_Stream>
			<SSDDevice.IO_Stream>
					 <Stream_ID>1</Stream_ID>
					 <Average_Read_Transaction_Turnaround_Time>0</Average_Read_Transaction_Turnaround_Time>
					 <Average_Read_Transaction_Execution_Time>0</Average_Read_Transaction_Execution_Time>
					 <Average_Read_Transaction_Transfer_Time>0</Average_Read_Transaction_Transfer_Time>
					 <Average_Read_Transaction_Waiting_Time>0</Average_Read_Transaction_Waiting_Time>
					 <Average_Write_Transaction_Turnaround_Time>33751</Average_Write_Transaction_Turnaround_Time>
					 <Average_Write_Transaction_Execution_Time>749</Average_Write_Transaction_Execution_Time>
					 <Average_Write_Transaction_Transfer_Time>12</Average_Write_Transaction_Transfer_Time>
					 <Average_Write_Transaction_Waiting_Time>32988</Average_Write_Transaction_Waiting_Time>
			</SSDDevice.IO_Stream>
		</SSDDevice.HostInterface>
		<SSDDevice.FTL Issued_Flash_Read_CMD="946449" Issued_Flash_Interleaved_Read_CMD="0" Issued_Flash_Multiplane_Read_CMD="8852" Issued_Flash_Copyback_Read_CMD="0" Issued_Flash_Multiplane_Copyback_Read_CMD="0" Issued_Flash_Program_CMD="2077684" Issued_Flash_Interleaved_Program_CMD="0" Issued_Flash_Multiplane_Program_CMD="111026" Issued_Flash_Interleaved_Multiplane_Program_CMD="0" Issued_Flash_Copyback_Program_CMD="0" Issued_Flash_Multiplane_Copyback_Program_CMD="0" Issued_Flash_Erase_CMD="4925" Issued_Flash_Interleaved_Erase_CMD="0" Issued_Flash_Multiplane_Erase_CMD="107" Issued_Flash_Interleaved_Multiplane_Erase_CMD="0" Issued_Flash_Suspend_Program_CMD="0" Issued_Flash_Suspend_Erase_CMD="0" Issued_Flash_Read_CMD_For_Mapping="0" Issued_Flash_Program_CMD_For_Mapping="0" CMT_Hits="2299736" CMT_Hits_For_Read="0" CMT_Hits_For_Write="2299736" CMT_Misses="0" CMT_Misses_For_Read="0" CMT_Misses_For_Write="0" Total_CMT_Queries="2299736" Total_CMT_Queries_For_Reads="0" Total_CMT_Queries_For_Writes="2299736" Total_GC_Executions="5139" Average_Page_Movement_For_GC="0.000000" Total_WL_Executions="0" Average_Page_Movement_For_WL="-nan(ind)"/>
		<SSDDevice.TSU>
			<SSDDevice.TSU.User_Read_TR_Queue Name="User_Read_TR_Queue@0@0" No_Of_Transactions_Enqueued="0" No_Of_Transactions_Dequeued="0" Avg_Queue_Length="0.000000" Max_Queue_Length="0" STDev_Queue_Length="0.000000" Avg_Transaction_Waiting_Time="9223372036854775808" Max_Transaction_Waiting_Time="0"/>
			<SSDDevice.TSU.User_Read_TR_Queue Name="User_Read_TR_Queue@0@1" No_Of_Transactions_Enqueued="0" No_Of_Transactions_Dequeued="0" Avg_Queue_Length="0.000000" Max_Queue_Length="0" STDev_Queue_Length="0.000000" Avg_Transaction_Waiting_Time="9223372036854775808" Max_Transaction_Waiting_Time="0"/>
			<SSDDevice.TSU.User_Read_TR_Queue Name="User_Read_TR_Queue@0@2" No_Of_Transactions_Enqueued="0" No_Of_Transactions_Dequeued="0" Avg_Queue_Length="0.000000" Max_Queue_Length="0" STDev_Queue_Length="0.000000" Avg_Transaction_Waiting_Time="9223372036854775808" Max_Transaction_Waiting_Time="0"/>
			<SSDDevice.TSU.User_Read_TR_Queue Name="User_Read_TR_Queue@0@3" No_Of_Transactions_Enqueued="0" No_Of_Transactions_Dequeued="0" Avg_Queue_Length="0.000000" Max_Queue_Length="0" STDev_Queue_Length="0.000000" Avg_Transaction_Waiting_Time="9223372036854775808" Max_Transaction_Waiting_Time="0"/>
			<SSDDevice.TSU.User_Read_TR_Queue Name="User_Read_TR_Queue@1@0" No_Of_Transactions_Enqueued="0" No_Of_Transactions_Dequeued="0" Avg_Queue_Length="0.000000" Max_Queue_Length="0" STDev_Queue_Length="0.000000" Avg_Transaction_Waiting_Time="9223372036854775808" Max_Transaction_Waiting_Time="0"/>
			<SSDDevice.TSU.User_Read_TR_Queue Name="User_Read_TR_Queue@1@1" No_Of_Transactions_Enqueued="0" No_Of_Transactions_Dequeued="0" Avg_Queue_Length="0.000000" Max_Queue_Length="0" STDev_Queue_Length="0.000000" Avg_Transaction_Waiting_Time="9223372036854775808" Max_Transaction_Waiting_Time="0"/>
			<SSDDevice.TSU.User_Read_TR_Queue Name="User_Read_TR_Queue@1@2" No_Of_Transactions_Enqueued="0" No_Of_Transactions_Dequeued="0" Avg_Queue_Length="0.000000" Max_Queue_Length="0" STDev_Queue_Length="0.000000" Avg_Transaction_Waiting_Time="9223372036854775808" Max_Transaction_Waiting_Time="0"/>
			<SSDDevice.TSU.User_Read_TR_Queue Name="User_Read_TR_Queue@1@3" No_Of_Transactions_Enqueued="0" No_Of_Transactions_Dequeued="0" Avg_Queue_Length="0.000000" Max_Queue_Length="0" STDev_Queue_Length="0.000000" Avg_Transaction_Waiting_Time="9223372036854775808" Max_Transaction_Waiting_Time="0"/>
			<SSDDevice.TSU.User_Read_TR_Queue Name="User_Read_TR_Queue@2@0" No_Of_Transactions_Enqueued="0" No_Of_Transactions_Dequeued="0" Avg_Queue_Length="0.000000" Max_Queue_Length="0" STDev_Queue_Length="0.000000" Avg_Transaction_Waiting_Time="9223372036854775808" Max_Transaction_Waiting_Time="0"/>
			<SSDDevice.TSU.User_Read_TR_Queue Name="User_Read_TR_Queue@2@1" No_Of_Transactions_Enqueued="0" No_Of_Transactions_Dequeued="0" Avg_Queue_Length="0.000000" Max_Queue_Length="0" STDev_Queue_Length="0.000000" Avg_Transaction_Waiting_Time="9223372036854775808" Max_Transaction_Waiting_Time="0"/>
			<SSDDevice.TSU.User_Read_TR_Queue Name="User_Read_TR_Queue@2@2" No_Of_Transactions_Enqueued="0" No_Of_Transactions_Dequeued="0" Avg_Queue_Length="0.000000" Max_Queue_Length="0" STDev_Queue_Length="0.000000" Avg_Transaction_Waiting_Time="9223372036854775808" Max_Transaction_Waiting_Time="0"/>
			<SSDDevice.TSU.User_Read_TR_Queue Name="User_Read_TR_Queue@2@3" No_Of_Transactions_Enqueued="0" No_Of_Transactions_Dequeued="0" Avg_Queue_Length="0.000000" Max_Queue_Length="0" STDev_Queue_Length="0.000000" Avg_Transaction_Waiting_Time="9223372036854775808" Max_Transaction_Waiting_Time="0"/>
			<SSDDevice.TSU.User_Read_TR_Queue Name="User_Read_TR_Queue@3@0" No_Of_Transactions_Enqueued="0" No_Of_Transactions_Dequeued="0" Avg_Queue_Length="0.000000" Max_Queue_Length="0" STDev_Queue_Length="0.000000" Avg_Transaction_Waiting_Time="9223372036854775808" Max_Transaction_Waiting_Time="0"/>
			<SSDDevice.TSU.User_Read_TR_Queue Name="User_Read_TR_Queue@3@1" No_Of_Transactions_Enqueued="0" No_Of_Transactions_Dequeued="0" Avg_Queue_Length="0.000000" Max_Queue_Length="0" STDev_Queue_Length="0.000000" Avg_Transaction_Waiting_Time="9223372036854775808" Max_Transaction_Waiting_Time="0"/>
			<SSDDevice.TSU.User_Read_TR_Queue Name="User_Read_TR_Queue@3@2" No_Of_Transactions_Enqueued="0" No_Of_Transactions_Dequeued="0" Avg_Queue_Length="0.000000" Max_Queue_Length="0" STDev_Queue_Length="0.000000" Avg_Transaction_Waiting_Time="9223372036854775808" Max_Transaction_Waiting_Time="0"/>
			<SSDDevice.TSU.User_Read_TR_Queue Name="User_Read_TR_Queue@3@3" No_Of_Transactions_Enqueued="0" No_Of_Transactions_Dequeued="0" Avg_Queue_Length="0.000000" Max_Queue_Length="0" STDev_Queue_Length="0.000000" Avg_Transaction_Waiting_Time="9223372036854775808" Max_Transaction_Waiting_Time="0"/>
			<SSDDevice.TSU.User_Read_TR_Queue Name="User_Read_TR_Queue@4@0" No_Of_Transactions_Enqueued="0" No_Of_Transactions_Dequeued="0" Avg_Queue_Length="0.000000" Max_Queue_Length="0" STDev_Queue_Length="0.000000" Avg_Transaction_Waiting_Time="9223372036854775808" Max_Transaction_Waiting_Time="0"/>
			<SSDDevice.TSU.User_Read_TR_Queue Name="User_Read_TR_Queue@4@1" No_Of_Transactions_Enqueued="0" No_Of_Transactions_Dequeued="0" Avg_Queue_Length="0.000000" Max_Queue_Length="0" STDev_Queue_Length="0.000000" Avg_Transaction_Waiting_Time="9223372036854775808" Max_Transaction_Waiting_Time="0"/>
			<SSDDevice.TSU.User_Read_TR_Queue Name="User_Read_TR_Queue@4@2" No_Of_Transactions_Enqueued="0" No_Of_Transactions_Dequeued="0" Avg_Queue_Length="0.000000" Max_Queue_Length="0" STDev_Queue_Length="0.000000" Avg_Transaction_Waiting_Time="9223372036854775808" Max_Transaction_Waiting_Time="0"/>
			<SSDDevice.TSU.User_Read_TR_Queue Name="User_Read_TR_Queue@4@3" No_Of_Transactions_Enqueued="0" No_Of_Transactions_Dequeued="0" Avg_Queue_Length="0.000000" Max_Queue_Length="0" STDev_Queue_Length="0.000000" Avg_Transaction_Waiting_Time="9223372036854775808" Max_Transaction_Waiting_Time="0"/>
			<SSDDevice.TSU.User_Read_TR_Queue Name="User_Read_TR_Queue@5@0" No_Of_Transactions_Enqueued="0" No_Of_Transactions_Dequeued="0" Avg_Queue_Length="0.000000" Max_Queue_Length="0" STDev_Queue_Length="0.000000" Avg_Transaction_Waiting_Time="9223372036854775808" Max_Transaction_Waiting_Time="0"/>
			<SSDDevice.TSU.User_Read_TR_Queue Name="User_Read_TR_Queue@5@1" No_Of_Transactions_Enqueued="0" No_Of_Transactions_Dequeued="0" Avg_Queue_Length="0.000000" Max_Queue_Length="0" STDev_Queue_Length="0.000000" Avg_Transaction_Waiting_Time="9223372036854775808" Max_Transaction_Waiting_Time="0"/>
			<SSDDevice.TSU.User_Read_TR_Queue Name="User_Read_TR_Queue@5@2" No_Of_Transactions_Enqueued="0" No_Of_Transactions_Dequeued="0" Avg_Queue_Length="0.000000" Max_Queue_Length="0" STDev_Queue_Length="0.000000" Avg_Transaction_Waiting_Time="9223372036854775808" Max_Transaction_Waiting_Time="0"/>
			<SSDDevice.TSU.User_Read_TR_Queue Name="User_Read_TR_Queue@5@3" No_Of_Transactions_Enqueued="0" No_Of_Transactions_Dequeued="0" Avg_Queue_Length="0.000000" Max_Queue_Length="0" STDev_Queue_Length="0.000000" Avg_Transaction_Waiting_Time="9223372036854775808" Max_Transaction_Waiting_Time="0"/>
			<SSDDevice.TSU.User_Read_TR_Queue Name="User_Read_TR_Queue@6@0" No_Of_Transactions_Enqueued="0" No_Of_Transactions_Dequeued="0" Avg_Queue_Length="0.000000" Max_Queue_Length="0" STDev_Queue_Length="0.000000" Avg_Transaction_Waiting_Time="9223372036854775808" Max_Transaction_Waiting_Time="0"/>
			<SSDDevice.TSU.User_Read_TR_Queue Name="User_Read_TR_Queue@6@1" No_Of_Transactions_Enqueued="0" No_Of_Transactions_Dequeued="0" Avg_Queue_Length="0.000000" Max_Queue_Length="0" STDev_Queue_Length="0.000000" Avg_Transaction_Waiting_Time="9223372036854775808" Max_Transaction_Waiting_Time="0"/>
			<SSDDevice.TSU.User_Read_TR_Queue Name="User_Read_TR_Queue@6@2" No_Of_Transactions_Enqueued="0" No_Of_Transactions_Dequeued="0" Avg_Queue_Length="0.000000" Max_Queue_Length="0" STDev_Queue_Length="0.000000" Avg_Transaction_Waiting_Time="9223372036854775808" Max_Transaction_Waiting_Time="0"/>
			<SSDDevice.TSU.User_Read_TR_Queue Name="User_Read_TR_Queue@6@3" No_Of_Transactions_Enqueued="0" No_Of_Transactions_Dequeued="0" Avg_Queue_Length="0.000000" Max_Queue_Length="0" STDev_Queue_Length="0.000000" Avg_Transaction_Waiting_Time="9223372036854775808" Max_Transaction_Waiting_Time="0"/>
			<SSDDevice.TSU.User_Read_TR_Queue Name="User_Read_TR_Queue@7@0" No_Of_Transactions_Enqueued="0" No_Of_Transactions_Dequeued="0" Avg_Queue_Length="0.000000" Max_Queue_Length="0" STDev_Queue_Length="0.000000" Avg_Transaction_Waiting_Time="9223372036854775808" Max_Transaction_Waiting_Time="0"/>
			<SSDDevice.TSU.User_Read_TR_Queue Name="User_Read_TR_Queue@7@1" No_Of_Transactions_Enqueued="0" No_Of_Transactions_Dequeued="0" Avg_Queue_Length="0.000000" Max_Queue_Length="0" STDev_Queue_Length="0.000000" Avg_Transaction_Waiting_Time="9223372036854775808" Max_Transaction_Waiting_Time="0"/>
			<SSDDevice.TSU.User_Read_TR_Queue Name="User_Read_TR_Queue@7@2" No_Of_Transactions_Enqueued="0" No_Of_Transactions_Dequeued="0" Avg_Queue_Length="0.000000" Max_Queue_Length="0" STDev_Queue_Length="0.000000" Avg_Transaction_Waiting_Time="9223372036854775808" Max_Transaction_Waiting_Time="0"/>
			<SSDDevice.TSU.User_Read_TR_Queue Name="User_Read_TR_Queue@7@3" No_Of_Transactions_Enqueued="0" No_Of_Transactions_Dequeued="0" Avg_Queue_Length="0.000000" Max_Queue_Length="0" STDev_Queue_Length="0.000000" Avg_Transaction_Waiting_Time="9223372036854775808" Max_Transaction_Waiting_Time="0"/>
			<SSDDevice.TSU.User_Write_TR_Queue Name="User_Write_TR_Queue@0@0" No_Of_Transactions_Enqueued="19307" No_Of_Transactions_Dequeued="19307" Avg_Queue_Length="1.492395" Max_Queue_Length="66" STDev_Queue_Length="12.034195" Avg_Transaction_Waiting_Time="7765" Max_Transaction_Waiting_Time="384054"/>
			<SSDDevice.TSU.User_Write_TR_Queue Name="User_Write_TR_Queue@0@1" No_Of_Transactions_Enqueued="19266" No_Of_Transactions_Dequeued="19266" Avg_Queue_Length="1.284679" Max_Queue_Length="46" STDev_Queue_Length="8.621131" Avg_Transaction_Waiting_Time="6698" Max_Transaction_Waiting_Time="372039"/>
			<SSDDevice.TSU.User_Write_TR_Queue Name="User_Write_TR_Queue@0@2" No_Of_Transactions_Enqueued="19289" No_Of_Transactions_Dequeued="19289" Avg_Queue_Length="1.524408" Max_Queue_Length="69" STDev_Queue_Length="12.573275" Avg_Transaction_Waiting_Time="7939" Max_Transaction_Waiting_Time="345477"/>
			<SSDDevice.TSU.User_Write_TR_Queue Name="User_Write_TR_Queue@0@3" No_Of_Transactions_Enqueued="19240" No_Of_Transactions_Dequeued="19240" Avg_Queue_Length="1.493036" Max_Queue_Length="79" STDev_Queue_Length="13.188192" Avg_Transaction_Waiting_Time="7795" Max_Transaction_Waiting_Time="384644"/>
			<SSDDevice.TSU.User_Write_TR_Queue Name="User_Write_TR_Queue@1@0" No_Of_Transactions_Enqueued="19205" No_Of_Transactions_Dequeued="19205" Avg_Queue_Length="1.434109" Max_Queue_Length="52" STDev_Queue_Length="10.244239" Avg_Transaction_Waiting_Time="7501" Max_Transaction_Waiting_Time="401144"/>
			<SSDDevice.TSU.User_Write_TR_Queue Name="User_Write_TR_Queue@1@1" No_Of_Transactions_Enqueued="19293" No_Of_Transactions_Dequeued="19293" Avg_Queue_Length="1.296929" Max_Queue_Length="42" STDev_Queue_Length="8.307695" Avg_Transaction_Waiting_Time="6753" Max_Transaction_Waiting_Time="365033"/>
			<SSDDevice.TSU.User_Write_TR_Queue Name="User_Write_TR_Queue@1@2" No_Of_Transactions_Enqueued="19208" No_Of_Transactions_Dequeued="19208" Avg_Queue_Length="1.434993" Max_Queue_Length="59" STDev_Queue_Length="10.931238" Avg_Transaction_Waiting_Time="7504" Max_Transaction_Waiting_Time="367257"/>
			<SSDDevice.TSU.User_Write_TR_Queue Name="User_Write_TR_Queue@1@3" No_Of_Transactions_Enqueued="19263" No_Of_Transactions_Dequeued="19263" Avg_Queue_Length="1.402909" Max_Queue_Length="56" STDev_Queue_Length="10.407301" Avg_Transaction_Waiting_Time="7316" Max_Transaction_Waiting_Time="377393"/>
			<SSDDevice.TSU.User_Write_TR_Queue Name="User_Write_TR_Queue@2@0" No_Of_Transactions_Enqueued="19223" No_Of_Transactions_Dequeued="19223" Avg_Queue_Length="1.414568" Max_Queue_Length="62" STDev_Queue_Length="11.050593" Avg_Transaction_Waiting_Time="7392" Max_Transaction_Waiting_Time="409373"/>
			<SSDDevice.TSU.User_Write_TR_Queue Name="User_Write_TR_Queue@2@1" No_Of_Transactions_Enqueued="19263" No_Of_Transactions_Dequeued="19263" Avg_Queue_Length="1.485713" Max_Queue_Length="55" STDev_Queue_Length="10.920597" Avg_Transaction_Waiting_Time="7748" Max_Transaction_Waiting_Time="375763"/>
			<SSDDevice.TSU.User_Write_TR_Queue Name="User_Write_TR_Queue@2@2" No_Of_Transactions_Enqueued="19240" No_Of_Transactions_Dequeued="19240" Avg_Queue_Length="1.305737" Max_Queue_Length="48" STDev_Queue_Length="8.954736" Avg_Transaction_Waiting_Time="6817" Max_Transaction_Waiting_Time="364483"/>
			<SSDDevice.TSU.User_Write_TR_Queue Name="User_Write_TR_Queue@2@3" No_Of_Transactions_Enqueued="19280" No_Of_Transactions_Dequeued="19280" Avg_Queue_Length="1.404643" Max_Queue_Length="45" STDev_Queue_Length="9.320358" Avg_Transaction_Waiting_Time="7318" Max_Transaction_Waiting_Time="307806"/>
			<SSDDevice.TSU.User_Write_TR_Queue Name="User_Write_TR_Queue@3@0" No_Of_Transactions_Enqueued="19179" No_Of_Transactions_Dequeued="19179" Avg_Queue_Length="1.482760" Max_Queue_Length="50" STDev_Queue_Length="10.382589" Avg_Transaction_Waiting_Time="7766" Max_Transaction_Waiting_Time="386844"/>
			<SSDDevice.TSU.User_Write_TR_Queue Name="User_Write_TR_Queue@3@1" No_Of_Transactions_Enqueued="19281" No_Of_Transactions_Dequeued="19281" Avg_Queue_Length="1.487118" Max_Queue_Length="46" STDev_Queue_Length="9.979473" Avg_Transaction_Waiting_Time="7748" Max_Transaction_Waiting_Time="329455"/>
			<SSDDevice.TSU.User_Write_TR_Queue Name="User_Write_TR_Queue@3@2" No_Of_Transactions_Enqueued="19218" No_Of_Transactions_Dequeued="19218" Avg_Queue_Length="1.303053" Max_Queue_Length="42" STDev_Queue_Length="8.347242" Avg_Transaction_Waiting_Time="6811" Max_Transaction_Waiting_Time="371972"/>
			<SSDDevice.TSU.User_Write_TR_Queue Name="User_Write_TR_Queue@3@3" No_Of_Transactions_Enqueued="19285" No_Of_Transactions_Dequeued="19285" Avg_Queue_Length="1.243010" Max_Queue_Length="44" STDev_Queue_Length="8.153842" Avg_Transaction_Waiting_Time="6474" Max_Transaction_Waiting_Time="291701"/>
			<SSDDevice.TSU.User_Write_TR_Queue Name="User_Write_TR_Queue@4@0" No_Of_Transactions_Enqueued="64365" No_Of_Transactions_Dequeued="64365" Avg_Queue_Length="13.530565" Max_Queue_Length="145" STDev_Queue_Length="162.374874" Avg_Transaction_Waiting_Time="21117" Max_Transaction_Waiting_Time="324925"/>
			<SSDDevice.TSU.User_Write_TR_Queue Name="User_Write_TR_Queue@4@1" No_Of_Transactions_Enqueued="63852" No_Of_Transactions_Dequeued="63852" Avg_Queue_Length="13.960486" Max_Queue_Length="140" STDev_Queue_Length="164.599336" Avg_Transaction_Waiting_Time="21963" Max_Transaction_Waiting_Time="358984"/>
			<SSDDevice.TSU.User_Write_TR_Queue Name="User_Write_TR_Queue@4@2" No_Of_Transactions_Enqueued="64608" No_Of_Transactions_Dequeued="64608" Avg_Queue_Length="12.631614" Max_Queue_Length="139" STDev_Queue_Length="148.394937" Avg_Transaction_Waiting_Time="19640" Max_Transaction_Waiting_Time="358051"/>
			<SSDDevice.TSU.User_Write_TR_Queue Name="User_Write_TR_Queue@4@3" No_Of_Transactions_Enqueued="64361" No_Of_Transactions_Dequeued="64361" Avg_Queue_Length="12.688580" Max_Queue_Length="135" STDev_Queue_Length="146.887479" Avg_Transaction_Waiting_Time="19804" Max_Transaction_Waiting_Time="372254"/>
			<SSDDevice.TSU.User_Write_TR_Queue Name="User_Write_TR_Queue@5@0" No_Of_Transactions_Enqueued="64226" No_Of_Transactions_Dequeued="64226" Avg_Queue_Length="12.231302" Max_Queue_Length="117" STDev_Queue_Length="131.743122" Avg_Transaction_Waiting_Time="19131" Max_Transaction_Waiting_Time="355138"/>
			<SSDDevice.TSU.User_Write_TR_Queue Name="User_Write_TR_Queue@5@1" No_Of_Transactions_Enqueued="64328" No_Of_Transactions_Dequeued="64328" Avg_Queue_Length="14.339386" Max_Queue_Length="170" STDev_Queue_Length="186.417616" Avg_Transaction_Waiting_Time="22392" Max_Transaction_Waiting_Time="359268"/>
			<SSDDevice.TSU.User_Write_TR_Queue Name="User_Write_TR_Queue@5@2" No_Of_Transactions_Enqueued="64387" No_Of_Transactions_Dequeued="64387" Avg_Queue_Length="13.380006" Max_Queue_Length="119" STDev_Queue_Length="145.351521" Avg_Transaction_Waiting_Time="20875" Max_Transaction_Waiting_Time="385167"/>
			<SSDDevice.TSU.User_Write_TR_Queue Name="User_Write_TR_Queue@5@3" No_Of_Transactions_Enqueued="64085" No_Of_Transactions_Dequeued="64085" Avg_Queue_Length="12.973177" Max_Queue_Length="110" STDev_Queue_Length="135.451970" Avg_Transaction_Waiting_Time="20336" Max_Transaction_Waiting_Time="370307"/>
			<SSDDevice.TSU.User_Write_TR_Queue Name="User_Write_TR_Queue@6@0" No_Of_Transactions_Enqueued="64335" No_Of_Transactions_Dequeued="64335" Avg_Queue_Length="12.948858" Max_Queue_Length="115" STDev_Queue_Length="138.265177" Avg_Transaction_Waiting_Time="20219" Max_Transaction_Waiting_Time="328091"/>
			<SSDDevice.TSU.User_Write_TR_Queue Name="User_Write_TR_Queue@6@1" No_Of_Transactions_Enqueued="64278" No_Of_Transactions_Dequeued="64278" Avg_Queue_Length="14.329357" Max_Queue_Length="176" STDev_Queue_Length="189.565231" Avg_Transaction_Waiting_Time="22394" Max_Transaction_Waiting_Time="368010"/>
			<SSDDevice.TSU.User_Write_TR_Queue Name="User_Write_TR_Queue@6@2" No_Of_Transactions_Enqueued="64245" No_Of_Transactions_Dequeued="64245" Avg_Queue_Length="12.733284" Max_Queue_Length="130" STDev_Queue_Length="144.629673" Avg_Transaction_Waiting_Time="19910" Max_Transaction_Waiting_Time="351928"/>
			<SSDDevice.TSU.User_Write_TR_Queue Name="User_Write_TR_Queue@6@3" No_Of_Transactions_Enqueued="63804" No_Of_Transactions_Dequeued="63804" Avg_Queue_Length="13.379385" Max_Queue_Length="162" STDev_Queue_Length="169.772332" Avg_Transaction_Waiting_Time="21065" Max_Transaction_Waiting_Time="355906"/>
			<SSDDevice.TSU.User_Write_TR_Queue Name="User_Write_TR_Queue@7@0" No_Of_Transactions_Enqueued="64197" No_Of_Transactions_Dequeued="64197" Avg_Queue_Length="12.048154" Max_Queue_Length="123" STDev_Queue_Length="133.084194" Avg_Transaction_Waiting_Time="18853" Max_Transaction_Waiting_Time="315846"/>
			<SSDDevice.TSU.User_Write_TR_Queue Name="User_Write_TR_Queue@7@1" No_Of_Transactions_Enqueued="64079" No_Of_Transactions_Dequeued="64079" Avg_Queue_Length="12.467454" Max_Queue_Length="142" STDev_Queue_Length="148.049663" Avg_Transaction_Waiting_Time="19545" Max_Transaction_Waiting_Time="354947"/>
			<SSDDevice.TSU.User_Write_TR_Queue Name="User_Write_TR_Queue@7@2" No_Of_Transactions_Enqueued="63727" No_Of_Transactions_Dequeued="63727" Avg_Queue_Length="12.248785" Max_Queue_Length="101" STDev_Queue_Length="122.497375" Avg_Transaction_Waiting_Time="19308" Max_Transaction_Waiting_Time="495684"/>
			<SSDDevice.TSU.User_Write_TR_Queue Name="User_Write_TR_Queue@7@3" No_Of_Transactions_Enqueued="64666" No_Of_Transactions_Dequeued="64666" Avg_Queue_Length="13.749613" Max_Queue_Length="139" STDev_Queue_Length="161.529053" Avg_Transaction_Waiting_Time="21359" Max_Transaction_Waiting_Time="332833"/>
			<SSDDevice.TSU.Mapping_Read_TR_Queue Name="Mapping_Read_TR_Queue@0@0" No_Of_Transactions_Enqueued="0" No_Of_Transactions_Dequeued="0" Avg_Queue_Length="0.000000" Max_Queue_Length="0" STDev_Queue_Length="0.000000" Avg_Transaction_Waiting_Time="9223372036854775808" Max_Transaction_Waiting_Time="0"/>
			<SSDDevice.TSU.Mapping_Read_TR_Queue Name="Mapping_Read_TR_Queue@0@1" No_Of_Transactions_Enqueued="0" No_Of_Transactions_Dequeued="0" Avg_Queue_Length="0.000000" Max_Queue_Length="0" STDev_Queue_Length="0.000000" Avg_Transaction_Waiting_Time="9223372036854775808" Max_Transaction_Waiting_Time="0"/>
			<SSDDevice.TSU.Mapping_Read_TR_Queue Name="Mapping_Read_TR_Queue@0@2" No_Of_Transactions_Enqueued="0" No_Of_Transactions_Dequeued="0" Avg_Queue_Length="0.000000" Max_Queue_Length="0" STDev_Queue_Length="0.000000" Avg_Transaction_Waiting_Time="9223372036854775808" Max_Transaction_Waiting_Time="0"/>
			<SSDDevice.TSU.Mapping_Read_TR_Queue Name="Mapping_Read_TR_Queue@0@3" No_Of_Transactions_Enqueued="0" No_Of_Transactions_Dequeued="0" Avg_Queue_Length="0.000000" Max_Queue_Length="0" STDev_Queue_Length="0.000000" Avg_Transaction_Waiting_Time="9223372036854775808" Max_Transaction_Waiting_Time="0"/>
			<SSDDevice.TSU.Mapping_Read_TR_Queue Name="Mapping_Read_TR_Queue@1@0" No_Of_Transactions_Enqueued="0" No_Of_Transactions_Dequeued="0" Avg_Queue_Length="0.000000" Max_Queue_Length="0" STDev_Queue_Length="0.000000" Avg_Transaction_Waiting_Time="9223372036854775808" Max_Transaction_Waiting_Time="0"/>
			<SSDDevice.TSU.Mapping_Read_TR_Queue Name="Mapping_Read_TR_Queue@1@1" No_Of_Transactions_Enqueued="0" No_Of_Transactions_Dequeued="0" Avg_Queue_Length="0.000000" Max_Queue_Length="0" STDev_Queue_Length="0.000000" Avg_Transaction_Waiting_Time="9223372036854775808" Max_Transaction_Waiting_Time="0"/>
			<SSDDevice.TSU.Mapping_Read_TR_Queue Name="Mapping_Read_TR_Queue@1@2" No_Of_Transactions_Enqueued="0" No_Of_Transactions_Dequeued="0" Avg_Queue_Length="0.000000" Max_Queue_Length="0" STDev_Queue_Length="0.000000" Avg_Transaction_Waiting_Time="9223372036854775808" Max_Transaction_Waiting_Time="0"/>
			<SSDDevice.TSU.Mapping_Read_TR_Queue Name="Mapping_Read_TR_Queue@1@3" No_Of_Transactions_Enqueued="0" No_Of_Transactions_Dequeued="0" Avg_Queue_Length="0.000000" Max_Queue_Length="0" STDev_Queue_Length="0.000000" Avg_Transaction_Waiting_Time="9223372036854775808" Max_Transaction_Waiting_Time="0"/>
			<SSDDevice.TSU.Mapping_Read_TR_Queue Name="Mapping_Read_TR_Queue@2@0" No_Of_Transactions_Enqueued="0" No_Of_Transactions_Dequeued="0" Avg_Queue_Length="0.000000" Max_Queue_Length="0" STDev_Queue_Length="0.000000" Avg_Transaction_Waiting_Time="9223372036854775808" Max_Transaction_Waiting_Time="0"/>
			<SSDDevice.TSU.Mapping_Read_TR_Queue Name="Mapping_Read_TR_Queue@2@1" No_Of_Transactions_Enqueued="0" No_Of_Transactions_Dequeued="0" Avg_Queue_Length="0.000000" Max_Queue_Length="0" STDev_Queue_Length="0.000000" Avg_Transaction_Waiting_Time="9223372036854775808" Max_Transaction_Waiting_Time="0"/>
			<SSDDevice.TSU.Mapping_Read_TR_Queue Name="Mapping_Read_TR_Queue@2@2" No_Of_Transactions_Enqueued="0" No_Of_Transactions_Dequeued="0" Avg_Queue_Length="0.000000" Max_Queue_Length="0" STDev_Queue_Length="0.000000" Avg_Transaction_Waiting_Time="9223372036854775808" Max_Transaction_Waiting_Time="0"/>
			<SSDDevice.TSU.Mapping_Read_TR_Queue Name="Mapping_Read_TR_Queue@2@3" No_Of_Transactions_Enqueued="0" No_Of_Transactions_Dequeued="0" Avg_Queue_Length="0.000000" Max_Queue_Length="0" STDev_Queue_Length="0.000000" Avg_Transaction_Waiting_Time="9223372036854775808" Max_Transaction_Waiting_Time="0"/>
			<SSDDevice.TSU.Mapping_Read_TR_Queue Name="Mapping_Read_TR_Queue@3@0" No_Of_Transactions_Enqueued="0" No_Of_Transactions_Dequeued="0" Avg_Queue_Length="0.000000" Max_Queue_Length="0" STDev_Queue_Length="0.000000" Avg_Transaction_Waiting_Time="9223372036854775808" Max_Transaction_Waiting_Time="0"/>
			<SSDDevice.TSU.Mapping_Read_TR_Queue Name="Mapping_Read_TR_Queue@3@1" No_Of_Transactions_Enqueued="0" No_Of_Transactions_Dequeued="0" Avg_Queue_Length="0.000000" Max_Queue_Length="0" STDev_Queue_Length="0.000000" Avg_Transaction_Waiting_Time="9223372036854775808" Max_Transaction_Waiting_Time="0"/>
			<SSDDevice.TSU.Mapping_Read_TR_Queue Name="Mapping_Read_TR_Queue@3@2" No_Of_Transactions_Enqueued="0" No_Of_Transactions_Dequeued="0" Avg_Queue_Length="0.000000" Max_Queue_Length="0" STDev_Queue_Length="0.000000" Avg_Transaction_Waiting_Time="9223372036854775808" Max_Transaction_Waiting_Time="0"/>
			<SSDDevice.TSU.Mapping_Read_TR_Queue Name="Mapping_Read_TR_Queue@3@3" No_Of_Transactions_Enqueued="0" No_Of_Transactions_Dequeued="0" Avg_Queue_Length="0.000000" Max_Queue_Length="0" STDev_Queue_Length="0.000000" Avg_Transaction_Waiting_Time="9223372036854775808" Max_Transaction_Waiting_Time="0"/>
			<SSDDevice.TSU.Mapping_Read_TR_Queue Name="Mapping_Read_TR_Queue@4@0" No_Of_Transactions_Enqueued="0" No_Of_Transactions_Dequeued="0" Avg_Queue_Length="0.000000" Max_Queue_Length="0" STDev_Queue_Length="0.000000" Avg_Transaction_Waiting_Time="9223372036854775808" Max_Transaction_Waiting_Time="0"/>
			<SSDDevice.TSU.Mapping_Read_TR_Queue Name="Mapping_Read_TR_Queue@4@1" No_Of_Transactions_Enqueued="0" No_Of_Transactions_Dequeued="0" Avg_Queue_Length="0.000000" Max_Queue_Length="0" STDev_Queue_Length="0.000000" Avg_Transaction_Waiting_Time="9223372036854775808" Max_Transaction_Waiting_Time="0"/>
			<SSDDevice.TSU.Mapping_Read_TR_Queue Name="Mapping_Read_TR_Queue@4@2" No_Of_Transactions_Enqueued="0" No_Of_Transactions_Dequeued="0" Avg_Queue_Length="0.000000" Max_Queue_Length="0" STDev_Queue_Length="0.000000" Avg_Transaction_Waiting_Time="9223372036854775808" Max_Transaction_Waiting_Time="0"/>
			<SSDDevice.TSU.Mapping_Read_TR_Queue Name="Mapping_Read_TR_Queue@4@3" No_Of_Transactions_Enqueued="0" No_Of_Transactions_Dequeued="0" Avg_Queue_Length="0.000000" Max_Queue_Length="0" STDev_Queue_Length="0.000000" Avg_Transaction_Waiting_Time="9223372036854775808" Max_Transaction_Waiting_Time="0"/>
			<SSDDevice.TSU.Mapping_Read_TR_Queue Name="Mapping_Read_TR_Queue@5@0" No_Of_Transactions_Enqueued="0" No_Of_Transactions_Dequeued="0" Avg_Queue_Length="0.000000" Max_Queue_Length="0" STDev_Queue_Length="0.000000" Avg_Transaction_Waiting_Time="9223372036854775808" Max_Transaction_Waiting_Time="0"/>
			<SSDDevice.TSU.Mapping_Read_TR_Queue Name="Mapping_Read_TR_Queue@5@1" No_Of_Transactions_Enqueued="0" No_Of_Transactions_Dequeued="0" Avg_Queue_Length="0.000000" Max_Queue_Length="0" STDev_Queue_Length="0.000000" Avg_Transaction_Waiting_Time="9223372036854775808" Max_Transaction_Waiting_Time="0"/>
			<SSDDevice.TSU.Mapping_Read_TR_Queue Name="Mapping_Read_TR_Queue@5@2" No_Of_Transactions_Enqueued="0" No_Of_Transactions_Dequeued="0" Avg_Queue_Length="0.000000" Max_Queue_Length="0" STDev_Queue_Length="0.000000" Avg_Transaction_Waiting_Time="9223372036854775808" Max_Transaction_Waiting_Time="0"/>
			<SSDDevice.TSU.Mapping_Read_TR_Queue Name="Mapping_Read_TR_Queue@5@3" No_Of_Transactions_Enqueued="0" No_Of_Transactions_Dequeued="0" Avg_Queue_Length="0.000000" Max_Queue_Length="0" STDev_Queue_Length="0.000000" Avg_Transaction_Waiting_Time="9223372036854775808" Max_Transaction_Waiting_Time="0"/>
			<SSDDevice.TSU.Mapping_Read_TR_Queue Name="Mapping_Read_TR_Queue@6@0" No_Of_Transactions_Enqueued="0" No_Of_Transactions_Dequeued="0" Avg_Queue_Length="0.000000" Max_Queue_Length="0" STDev_Queue_Length="0.000000" Avg_Transaction_Waiting_Time="9223372036854775808" Max_Transaction_Waiting_Time="0"/>
			<SSDDevice.TSU.Mapping_Read_TR_Queue Name="Mapping_Read_TR_Queue@6@1" No_Of_Transactions_Enqueued="0" No_Of_Transactions_Dequeued="0" Avg_Queue_Length="0.000000" Max_Queue_Length="0" STDev_Queue_Length="0.000000" Avg_Transaction_Waiting_Time="9223372036854775808" Max_Transaction_Waiting_Time="0"/>
			<SSDDevice.TSU.Mapping_Read_TR_Queue Name="Mapping_Read_TR_Queue@6@2" No_Of_Transactions_Enqueued="0" No_Of_Transactions_Dequeued="0" Avg_Queue_Length="0.000000" Max_Queue_Length="0" STDev_Queue_Length="0.000000" Avg_Transaction_Waiting_Time="9223372036854775808" Max_Transaction_Waiting_Time="0"/>
			<SSDDevice.TSU.Mapping_Read_TR_Queue Name="Mapping_Read_TR_Queue@6@3" No_Of_Transactions_Enqueued="0" No_Of_Transactions_Dequeued="0" Avg_Queue_Length="0.000000" Max_Queue_Length="0" STDev_Queue_Length="0.000000" Avg_Transaction_Waiting_Time="9223372036854775808" Max_Transaction_Waiting_Time="0"/>
			<SSDDevice.TSU.Mapping_Read_TR_Queue Name="Mapping_Read_TR_Queue@7@0" No_Of_Transactions_Enqueued="0" No_Of_Transactions_Dequeued="0" Avg_Queue_Length="0.000000" Max_Queue_Length="0" STDev_Queue_Length="0.000000" Avg_Transaction_Waiting_Time="9223372036854775808" Max_Transaction_Waiting_Time="0"/>
			<SSDDevice.TSU.Mapping_Read_TR_Queue Name="Mapping_Read_TR_Queue@7@1" No_Of_Transactions_Enqueued="0" No_Of_Transactions_Dequeued="0" Avg_Queue_Length="0.000000" Max_Queue_Length="0" STDev_Queue_Length="0.000000" Avg_Transaction_Waiting_Time="9223372036854775808" Max_Transaction_Waiting_Time="0"/>
			<SSDDevice.TSU.Mapping_Read_TR_Queue Name="Mapping_Read_TR_Queue@7@2" No_Of_Transactions_Enqueued="0" No_Of_Transactions_Dequeued="0" Avg_Queue_Length="0.000000" Max_Queue_Length="0" STDev_Queue_Length="0.000000" Avg_Transaction_Waiting_Time="9223372036854775808" Max_Transaction_Waiting_Time="0"/>
			<SSDDevice.TSU.Mapping_Read_TR_Queue Name="Mapping_Read_TR_Queue@7@3" No_Of_Transactions_Enqueued="0" No_Of_Transactions_Dequeued="0" Avg_Queue_Length="0.000000" Max_Queue_Length="0" STDev_Queue_Length="0.000000" Avg_Transaction_Waiting_Time="9223372036854775808" Max_Transaction_Waiting_Time="0"/>
			<SSDDevice.TSU.Mapping_Write_TR_Queue Name="Mapping_Write_TR_Queue@0@0" No_Of_Transactions_Enqueued="0" No_Of_Transactions_Dequeued="0" Avg_Queue_Length="0.000000" Max_Queue_Length="0" STDev_Queue_Length="0.000000" Avg_Transaction_Waiting_Time="9223372036854775808" Max_Transaction_Waiting_Time="0"/>
			<SSDDevice.TSU.Mapping_Write_TR_Queue Name="Mapping_Write_TR_Queue@0@1" No_Of_Transactions_Enqueued="0" No_Of_Transactions_Dequeued="0" Avg_Queue_Length="0.000000" Max_Queue_Length="0" STDev_Queue_Length="0.000000" Avg_Transaction_Waiting_Time="9223372036854775808" Max_Transaction_Waiting_Time="0"/>
			<SSDDevice.TSU.Mapping_Write_TR_Queue Name="Mapping_Write_TR_Queue@0@2" No_Of_Transactions_Enqueued="0" No_Of_Transactions_Dequeued="0" Avg_Queue_Length="0.000000" Max_Queue_Length="0" STDev_Queue_Length="0.000000" Avg_Transaction_Waiting_Time="9223372036854775808" Max_Transaction_Waiting_Time="0"/>
			<SSDDevice.TSU.Mapping_Write_TR_Queue Name="Mapping_Write_TR_Queue@0@3" No_Of_Transactions_Enqueued="0" No_Of_Transactions_Dequeued="0" Avg_Queue_Length="0.000000" Max_Queue_Length="0" STDev_Queue_Length="0.000000" Avg_Transaction_Waiting_Time="9223372036854775808" Max_Transaction_Waiting_Time="0"/>
			<SSDDevice.TSU.Mapping_Write_TR_Queue Name="Mapping_Write_TR_Queue@1@0" No_Of_Transactions_Enqueued="0" No_Of_Transactions_Dequeued="0" Avg_Queue_Length="0.000000" Max_Queue_Length="0" STDev_Queue_Length="0.000000" Avg_Transaction_Waiting_Time="9223372036854775808" Max_Transaction_Waiting_Time="0"/>
			<SSDDevice.TSU.Mapping_Write_TR_Queue Name="Mapping_Write_TR_Queue@1@1" No_Of_Transactions_Enqueued="0" No_Of_Transactions_Dequeued="0" Avg_Queue_Length="0.000000" Max_Queue_Length="0" STDev_Queue_Length="0.000000" Avg_Transaction_Waiting_Time="9223372036854775808" Max_Transaction_Waiting_Time="0"/>
			<SSDDevice.TSU.Mapping_Write_TR_Queue Name="Mapping_Write_TR_Queue@1@2" No_Of_Transactions_Enqueued="0" No_Of_Transactions_Dequeued="0" Avg_Queue_Length="0.000000" Max_Queue_Length="0" STDev_Queue_Length="0.000000" Avg_Transaction_Waiting_Time="9223372036854775808" Max_Transaction_Waiting_Time="0"/>
			<SSDDevice.TSU.Mapping_Write_TR_Queue Name="Mapping_Write_TR_Queue@1@3" No_Of_Transactions_Enqueued="0" No_Of_Transactions_Dequeued="0" Avg_Queue_Length="0.000000" Max_Queue_Length="0" STDev_Queue_Length="0.000000" Avg_Transaction_Waiting_Time="9223372036854775808" Max_Transaction_Waiting_Time="0"/>
			<SSDDevice.TSU.Mapping_Write_TR_Queue Name="Mapping_Write_TR_Queue@2@0" No_Of_Transactions_Enqueued="0" No_Of_Transactions_Dequeued="0" Avg_Queue_Length="0.000000" Max_Queue_Length="0" STDev_Queue_Length="0.000000" Avg_Transaction_Waiting_Time="9223372036854775808" Max_Transaction_Waiting_Time="0"/>
			<SSDDevice.TSU.Mapping_Write_TR_Queue Name="Mapping_Write_TR_Queue@2@1" No_Of_Transactions_Enqueued="0" No_Of_Transactions_Dequeued="0" Avg_Queue_Length="0.000000" Max_Queue_Length="0" STDev_Queue_Length="0.000000" Avg_Transaction_Waiting_Time="9223372036854775808" Max_Transaction_Waiting_Time="0"/>
			<SSDDevice.TSU.Mapping_Write_TR_Queue Name="Mapping_Write_TR_Queue@2@2" No_Of_Transactions_Enqueued="0" No_Of_Transactions_Dequeued="0" Avg_Queue_Length="0.000000" Max_Queue_Length="0" STDev_Queue_Length="0.000000" Avg_Transaction_Waiting_Time="9223372036854775808" Max_Transaction_Waiting_Time="0"/>
			<SSDDevice.TSU.Mapping_Write_TR_Queue Name="Mapping_Write_TR_Queue@2@3" No_Of_Transactions_Enqueued="0" No_Of_Transactions_Dequeued="0" Avg_Queue_Length="0.000000" Max_Queue_Length="0" STDev_Queue_Length="0.000000" Avg_Transaction_Waiting_Time="9223372036854775808" Max_Transaction_Waiting_Time="0"/>
			<SSDDevice.TSU.Mapping_Write_TR_Queue Name="Mapping_Write_TR_Queue@3@0" No_Of_Transactions_Enqueued="0" No_Of_Transactions_Dequeued="0" Avg_Queue_Length="0.000000" Max_Queue_Length="0" STDev_Queue_Length="0.000000" Avg_Transaction_Waiting_Time="9223372036854775808" Max_Transaction_Waiting_Time="0"/>
			<SSDDevice.TSU.Mapping_Write_TR_Queue Name="Mapping_Write_TR_Queue@3@1" No_Of_Transactions_Enqueued="0" No_Of_Transactions_Dequeued="0" Avg_Queue_Length="0.000000" Max_Queue_Length="0" STDev_Queue_Length="0.000000" Avg_Transaction_Waiting_Time="9223372036854775808" Max_Transaction_Waiting_Time="0"/>
			<SSDDevice.TSU.Mapping_Write_TR_Queue Name="Mapping_Write_TR_Queue@3@2" No_Of_Transactions_Enqueued="0" No_Of_Transactions_Dequeued="0" Avg_Queue_Length="0.000000" Max_Queue_Length="0" STDev_Queue_Length="0.000000" Avg_Transaction_Waiting_Time="9223372036854775808" Max_Transaction_Waiting_Time="0"/>
			<SSDDevice.TSU.Mapping_Write_TR_Queue Name="Mapping_Write_TR_Queue@3@3" No_Of_Transactions_Enqueued="0" No_Of_Transactions_Dequeued="0" Avg_Queue_Length="0.000000" Max_Queue_Length="0" STDev_Queue_Length="0.000000" Avg_Transaction_Waiting_Time="9223372036854775808" Max_Transaction_Waiting_Time="0"/>
			<SSDDevice.TSU.Mapping_Write_TR_Queue Name="Mapping_Write_TR_Queue@4@0" No_Of_Transactions_Enqueued="0" No_Of_Transactions_Dequeued="0" Avg_Queue_Length="0.000000" Max_Queue_Length="0" STDev_Queue_Length="0.000000" Avg_Transaction_Waiting_Time="9223372036854775808" Max_Transaction_Waiting_Time="0"/>
			<SSDDevice.TSU.Mapping_Write_TR_Queue Name="Mapping_Write_TR_Queue@4@1" No_Of_Transactions_Enqueued="0" No_Of_Transactions_Dequeued="0" Avg_Queue_Length="0.000000" Max_Queue_Length="0" STDev_Queue_Length="0.000000" Avg_Transaction_Waiting_Time="9223372036854775808" Max_Transaction_Waiting_Time="0"/>
			<SSDDevice.TSU.Mapping_Write_TR_Queue Name="Mapping_Write_TR_Queue@4@2" No_Of_Transactions_Enqueued="0" No_Of_Transactions_Dequeued="0" Avg_Queue_Length="0.000000" Max_Queue_Length="0" STDev_Queue_Length="0.000000" Avg_Transaction_Waiting_Time="9223372036854775808" Max_Transaction_Waiting_Time="0"/>
			<SSDDevice.TSU.Mapping_Write_TR_Queue Name="Mapping_Write_TR_Queue@4@3" No_Of_Transactions_Enqueued="0" No_Of_Transactions_Dequeued="0" Avg_Queue_Length="0.000000" Max_Queue_Length="0" STDev_Queue_Length="0.000000" Avg_Transaction_Waiting_Time="9223372036854775808" Max_Transaction_Waiting_Time="0"/>
			<SSDDevice.TSU.Mapping_Write_TR_Queue Name="Mapping_Write_TR_Queue@5@0" No_Of_Transactions_Enqueued="0" No_Of_Transactions_Dequeued="0" Avg_Queue_Length="0.000000" Max_Queue_Length="0" STDev_Queue_Length="0.000000" Avg_Transaction_Waiting_Time="9223372036854775808" Max_Transaction_Waiting_Time="0"/>
			<SSDDevice.TSU.Mapping_Write_TR_Queue Name="Mapping_Write_TR_Queue@5@1" No_Of_Transactions_Enqueued="0" No_Of_Transactions_Dequeued="0" Avg_Queue_Length="0.000000" Max_Queue_Length="0" STDev_Queue_Length="0.000000" Avg_Transaction_Waiting_Time="9223372036854775808" Max_Transaction_Waiting_Time="0"/>
			<SSDDevice.TSU.Mapping_Write_TR_Queue Name="Mapping_Write_TR_Queue@5@2" No_Of_Transactions_Enqueued="0" No_Of_Transactions_Dequeued="0" Avg_Queue_Length="0.000000" Max_Queue_Length="0" STDev_Queue_Length="0.000000" Avg_Transaction_Waiting_Time="9223372036854775808" Max_Transaction_Waiting_Time="0"/>
			<SSDDevice.TSU.Mapping_Write_TR_Queue Name="Mapping_Write_TR_Queue@5@3" No_Of_Transactions_Enqueued="0" No_Of_Transactions_Dequeued="0" Avg_Queue_Length="0.000000" Max_Queue_Length="0" STDev_Queue_Length="0.000000" Avg_Transaction_Waiting_Time="9223372036854775808" Max_Transaction_Waiting_Time="0"/>
			<SSDDevice.TSU.Mapping_Write_TR_Queue Name="Mapping_Write_TR_Queue@6@0" No_Of_Transactions_Enqueued="0" No_Of_Transactions_Dequeued="0" Avg_Queue_Length="0.000000" Max_Queue_Length="0" STDev_Queue_Length="0.000000" Avg_Transaction_Waiting_Time="9223372036854775808" Max_Transaction_Waiting_Time="0"/>
			<SSDDevice.TSU.Mapping_Write_TR_Queue Name="Mapping_Write_TR_Queue@6@1" No_Of_Transactions_Enqueued="0" No_Of_Transactions_Dequeued="0" Avg_Queue_Length="0.000000" Max_Queue_Length="0" STDev_Queue_Length="0.000000" Avg_Transaction_Waiting_Time="9223372036854775808" Max_Transaction_Waiting_Time="0"/>
			<SSDDevice.TSU.Mapping_Write_TR_Queue Name="Mapping_Write_TR_Queue@6@2" No_Of_Transactions_Enqueued="0" No_Of_Transactions_Dequeued="0" Avg_Queue_Length="0.000000" Max_Queue_Length="0" STDev_Queue_Length="0.000000" Avg_Transaction_Waiting_Time="9223372036854775808" Max_Transaction_Waiting_Time="0"/>
			<SSDDevice.TSU.Mapping_Write_TR_Queue Name="Mapping_Write_TR_Queue@6@3" No_Of_Transactions_Enqueued="0" No_Of_Transactions_Dequeued="0" Avg_Queue_Length="0.000000" Max_Queue_Length="0" STDev_Queue_Length="0.000000" Avg_Transaction_Waiting_Time="9223372036854775808" Max_Transaction_Waiting_Time="0"/>
			<SSDDevice.TSU.Mapping_Write_TR_Queue Name="Mapping_Write_TR_Queue@7@0" No_Of_Transactions_Enqueued="0" No_Of_Transactions_Dequeued="0" Avg_Queue_Length="0.000000" Max_Queue_Length="0" STDev_Queue_Length="0.000000" Avg_Transaction_Waiting_Time="9223372036854775808" Max_Transaction_Waiting_Time="0"/>
			<SSDDevice.TSU.Mapping_Write_TR_Queue Name="Mapping_Write_TR_Queue@7@1" No_Of_Transactions_Enqueued="0" No_Of_Transactions_Dequeued="0" Avg_Queue_Length="0.000000" Max_Queue_Length="0" STDev_Queue_Length="0.000000" Avg_Transaction_Waiting_Time="9223372036854775808" Max_Transaction_Waiting_Time="0"/>
			<SSDDevice.TSU.Mapping_Write_TR_Queue Name="Mapping_Write_TR_Queue@7@2" No_Of_Transactions_Enqueued="0" No_Of_Transactions_Dequeued="0" Avg_Queue_Length="0.000000" Max_Queue_Length="0" STDev_Queue_Length="0.000000" Avg_Transaction_Waiting_Time="9223372036854775808" Max_Transaction_Waiting_Time="0"/>
			<SSDDevice.TSU.Mapping_Write_TR_Queue Name="Mapping_Write_TR_Queue@7@3" No_Of_Transactions_Enqueued="0" No_Of_Transactions_Dequeued="0" Avg_Queue_Length="0.000000" Max_Queue_Length="0" STDev_Queue_Length="0.000000" Avg_Transaction_Waiting_Time="9223372036854775808" Max_Transaction_Waiting_Time="0"/>
			<SSDDevice.TSU.GC_Read_TR_Queue Name="GC_Read_TR_Queue@0@0" No_Of_Transactions_Enqueued="14471" No_Of_Transactions_Dequeued="14471" Avg_Queue_Length="1.610663" Max_Queue_Length="365" STDev_Queue_Length="30.729735" Avg_Transaction_Waiting_Time="11181" Max_Transaction_Waiting_Time="30536"/>
			<SSDDevice.TSU.GC_Read_TR_Queue Name="GC_Read_TR_Queue@0@1" No_Of_Transactions_Enqueued="14104" No_Of_Transactions_Dequeued="14104" Avg_Queue_Length="1.569761" Max_Queue_Length="407" STDev_Queue_Length="31.630018" Avg_Transaction_Waiting_Time="11180" Max_Transaction_Waiting_Time="32386"/>
			<SSDDevice.TSU.GC_Read_TR_Queue Name="GC_Read_TR_Queue@0@2" No_Of_Transactions_Enqueued="14048" No_Of_Transactions_Dequeued="14048" Avg_Queue_Length="1.540539" Max_Queue_Length="285" STDev_Queue_Length="25.961917" Avg_Transaction_Waiting_Time="11016" Max_Transaction_Waiting_Time="32650"/>
			<SSDDevice.TSU.GC_Read_TR_Queue Name="GC_Read_TR_Queue@0@3" No_Of_Transactions_Enqueued="14304" No_Of_Transactions_Dequeued="14304" Avg_Queue_Length="1.595279" Max_Queue_Length="339" STDev_Queue_Length="29.329118" Avg_Transaction_Waiting_Time="11203" Max_Transaction_Waiting_Time="29440"/>
			<SSDDevice.TSU.GC_Read_TR_Queue Name="GC_Read_TR_Queue@1@0" No_Of_Transactions_Enqueued="14078" No_Of_Transactions_Dequeued="14078" Avg_Queue_Length="1.563985" Max_Queue_Length="379" STDev_Queue_Length="30.407580" Avg_Transaction_Waiting_Time="11160" Max_Transaction_Waiting_Time="37096"/>
			<SSDDevice.TSU.GC_Read_TR_Queue Name="GC_Read_TR_Queue@1@1" No_Of_Transactions_Enqueued="14075" No_Of_Transactions_Dequeued="14075" Avg_Queue_Length="1.570707" Max_Queue_Length="397" STDev_Queue_Length="31.256901" Avg_Transaction_Waiting_Time="11210" Max_Transaction_Waiting_Time="30101"/>
			<SSDDevice.TSU.GC_Read_TR_Queue Name="GC_Read_TR_Queue@1@2" No_Of_Transactions_Enqueued="13893" No_Of_Transactions_Dequeued="13893" Avg_Queue_Length="1.568050" Max_Queue_Length="366" STDev_Queue_Length="29.957791" Avg_Transaction_Waiting_Time="11338" Max_Transaction_Waiting_Time="38840"/>
			<SSDDevice.TSU.GC_Read_TR_Queue Name="GC_Read_TR_Queue@1@3" No_Of_Transactions_Enqueued="14466" No_Of_Transactions_Dequeued="14466" Avg_Queue_Length="1.634772" Max_Queue_Length="495" STDev_Queue_Length="36.334825" Avg_Transaction_Waiting_Time="11352" Max_Transaction_Waiting_Time="46452"/>
			<SSDDevice.TSU.GC_Read_TR_Queue Name="GC_Read_TR_Queue@2@0" No_Of_Transactions_Enqueued="14086" No_Of_Transactions_Dequeued="14086" Avg_Queue_Length="1.632281" Max_Queue_Length="402" STDev_Queue_Length="32.686626" Avg_Transaction_Waiting_Time="11640" Max_Transaction_Waiting_Time="34646"/>
			<SSDDevice.TSU.GC_Read_TR_Queue Name="GC_Read_TR_Queue@2@1" No_Of_Transactions_Enqueued="14488" No_Of_Transactions_Dequeued="14488" Avg_Queue_Length="1.682093" Max_Queue_Length="385" STDev_Queue_Length="32.962410" Avg_Transaction_Waiting_Time="11663" Max_Transaction_Waiting_Time="34975"/>
			<SSDDevice.TSU.GC_Read_TR_Queue Name="GC_Read_TR_Queue@2@2" No_Of_Transactions_Enqueued="13727" No_Of_Transactions_Dequeued="13727" Avg_Queue_Length="1.531130" Max_Queue_Length="327" STDev_Queue_Length="27.645544" Avg_Transaction_Waiting_Time="11205" Max_Transaction_Waiting_Time="31652"/>
			<SSDDevice.TSU.GC_Read_TR_Queue Name="GC_Read_TR_Queue@2@3" No_Of_Transactions_Enqueued="13722" No_Of_Transactions_Dequeued="13722" Avg_Queue_Length="1.572339" Max_Queue_Length="352" STDev_Queue_Length="29.457995" Avg_Transaction_Waiting_Time="11510" Max_Transaction_Waiting_Time="34740"/>
			<SSDDevice.TSU.GC_Read_TR_Queue Name="GC_Read_TR_Queue@3@0" No_Of_Transactions_Enqueued="14111" No_Of_Transactions_Dequeued="14111" Avg_Queue_Length="1.609745" Max_Queue_Length="390" STDev_Queue_Length="31.749362" Avg_Transaction_Waiting_Time="11459" Max_Transaction_Waiting_Time="37871"/>
			<SSDDevice.TSU.GC_Read_TR_Queue Name="GC_Read_TR_Queue@3@1" No_Of_Transactions_Enqueued="14506" No_Of_Transactions_Dequeued="14506" Avg_Queue_Length="1.605227" Max_Queue_Length="403" STDev_Queue_Length="32.184936" Avg_Transaction_Waiting_Time="11116" Max_Transaction_Waiting_Time="33677"/>
			<SSDDevice.TSU.GC_Read_TR_Queue Name="GC_Read_TR_Queue@3@2" No_Of_Transactions_Enqueued="14081" No_Of_Transactions_Dequeued="14081" Avg_Queue_Length="1.589623" Max_Queue_Length="545" STDev_Queue_Length="37.076266" Avg_Transaction_Waiting_Time="11340" Max_Transaction_Waiting_Time="37816"/>
			<SSDDevice.TSU.GC_Read_TR_Queue Name="GC_Read_TR_Queue@3@3" No_Of_Transactions_Enqueued="13707" No_Of_Transactions_Dequeued="13707" Avg_Queue_Length="1.528529" Max_Queue_Length="408" STDev_Queue_Length="30.837112" Avg_Transaction_Waiting_Time="11202" Max_Transaction_Waiting_Time="34099"/>
			<SSDDevice.TSU.GC_Read_TR_Queue Name="GC_Read_TR_Queue@4@0" No_Of_Transactions_Enqueued="46661" No_Of_Transactions_Dequeued="46661" Avg_Queue_Length="4.683079" Max_Queue_Length="306" STDev_Queue_Length="81.787320" Avg_Transaction_Waiting_Time="10082" Max_Transaction_Waiting_Time="28133"/>
			<SSDDevice.TSU.GC_Read_TR_Queue Name="GC_Read_TR_Queue@4@1" No_Of_Transactions_Enqueued="45681" No_Of_Transactions_Dequeued="45681" Avg_Queue_Length="4.594151" Max_Queue_Length="359" STDev_Queue_Length="86.926183" Avg_Transaction_Waiting_Time="10103" Max_Transaction_Waiting_Time="30253"/>
			<SSDDevice.TSU.GC_Read_TR_Queue Name="GC_Read_TR_Queue@4@2" No_Of_Transactions_Enqueued="46372" No_Of_Transactions_Dequeued="46372" Avg_Queue_Length="4.722409" Max_Queue_Length="383" STDev_Queue_Length="92.299400" Avg_Transaction_Waiting_Time="10230" Max_Transaction_Waiting_Time="29465"/>
			<SSDDevice.TSU.GC_Read_TR_Queue Name="GC_Read_TR_Queue@4@3" No_Of_Transactions_Enqueued="46128" No_Of_Transactions_Dequeued="46128" Avg_Queue_Length="4.729987" Max_Queue_Length="375" STDev_Queue_Length="91.474305" Avg_Transaction_Waiting_Time="10300" Max_Transaction_Waiting_Time="29382"/>
			<SSDDevice.TSU.GC_Read_TR_Queue Name="GC_Read_TR_Queue@5@0" No_Of_Transactions_Enqueued="45799" No_Of_Transactions_Dequeued="45799" Avg_Queue_Length="4.579759" Max_Queue_Length="321" STDev_Queue_Length="81.926040" Avg_Transaction_Waiting_Time="10045" Max_Transaction_Waiting_Time="28256"/>
			<SSDDevice.TSU.GC_Read_TR_Queue Name="GC_Read_TR_Queue@5@1" No_Of_Transactions_Enqueued="46337" No_Of_Transactions_Dequeued="46337" Avg_Queue_Length="4.641645" Max_Queue_Length="373" STDev_Queue_Length="89.525545" Avg_Transaction_Waiting_Time="10062" Max_Transaction_Waiting_Time="29520"/>
			<SSDDevice.TSU.GC_Read_TR_Queue Name="GC_Read_TR_Queue@5@2" No_Of_Transactions_Enqueued="46073" No_Of_Transactions_Dequeued="46073" Avg_Queue_Length="4.655159" Max_Queue_Length="369" STDev_Queue_Length="89.302181" Avg_Transaction_Waiting_Time="10150" Max_Transaction_Waiting_Time="29265"/>
			<SSDDevice.TSU.GC_Read_TR_Queue Name="GC_Read_TR_Queue@5@3" No_Of_Transactions_Enqueued="45728" No_Of_Transactions_Dequeued="45728" Avg_Queue_Length="4.583206" Max_Queue_Length="340" STDev_Queue_Length="84.386564" Avg_Transaction_Waiting_Time="10068" Max_Transaction_Waiting_Time="28853"/>
			<SSDDevice.TSU.GC_Read_TR_Queue Name="GC_Read_TR_Queue@6@0" No_Of_Transactions_Enqueued="46391" No_Of_Transactions_Dequeued="46391" Avg_Queue_Length="4.668368" Max_Queue_Length="358" STDev_Queue_Length="88.206995" Avg_Transaction_Waiting_Time="10109" Max_Transaction_Waiting_Time="29975"/>
			<SSDDevice.TSU.GC_Read_TR_Queue Name="GC_Read_TR_Queue@6@1" No_Of_Transactions_Enqueued="46352" No_Of_Transactions_Dequeued="46352" Avg_Queue_Length="4.641792" Max_Queue_Length="378" STDev_Queue_Length="90.128054" Avg_Transaction_Waiting_Time="10060" Max_Transaction_Waiting_Time="26699"/>
			<SSDDevice.TSU.GC_Read_TR_Queue Name="GC_Read_TR_Queue@6@2" No_Of_Transactions_Enqueued="46204" No_Of_Transactions_Dequeued="46204" Avg_Queue_Length="4.627893" Max_Queue_Length="421" STDev_Queue_Length="94.844266" Avg_Transaction_Waiting_Time="10062" Max_Transaction_Waiting_Time="28384"/>
			<SSDDevice.TSU.GC_Read_TR_Queue Name="GC_Read_TR_Queue@6@3" No_Of_Transactions_Enqueued="45866" No_Of_Transactions_Dequeued="45866" Avg_Queue_Length="4.596962" Max_Queue_Length="359" STDev_Queue_Length="86.979384" Avg_Transaction_Waiting_Time="10068" Max_Transaction_Waiting_Time="27718"/>
			<SSDDevice.TSU.GC_Read_TR_Queue Name="GC_Read_TR_Queue@7@0" No_Of_Transactions_Enqueued="46125" No_Of_Transactions_Dequeued="46125" Avg_Queue_Length="4.580108" Max_Queue_Length="361" STDev_Queue_Length="86.902215" Avg_Transaction_Waiting_Time="9975" Max_Transaction_Waiting_Time="27647"/>
			<SSDDevice.TSU.GC_Read_TR_Queue Name="GC_Read_TR_Queue@7@1" No_Of_Transactions_Enqueued="46159" No_Of_Transactions_Dequeued="46159" Avg_Queue_Length="4.649334" Max_Queue_Length="316" STDev_Queue_Length="82.518318" Avg_Transaction_Waiting_Time="10118" Max_Transaction_Waiting_Time="29378"/>
			<SSDDevice.TSU.GC_Read_TR_Queue Name="GC_Read_TR_Queue@7@2" No_Of_Transactions_Enqueued="45865" No_Of_Transactions_Dequeued="45865" Avg_Queue_Length="4.590141" Max_Queue_Length="312" STDev_Queue_Length="80.948855" Avg_Transaction_Waiting_Time="10053" Max_Transaction_Waiting_Time="31833"/>
			<SSDDevice.TSU.GC_Read_TR_Queue Name="GC_Read_TR_Queue@7@3" No_Of_Transactions_Enqueued="46545" No_Of_Transactions_Dequeued="46545" Avg_Queue_Length="4.718661" Max_Queue_Length="364" STDev_Queue_Length="89.903310" Avg_Transaction_Waiting_Time="10184" Max_Transaction_Waiting_Time="31235"/>
			<SSDDevice.TSU.GC_Write_TR_Queue Name="GC_Write_TR_Queue@0@0" No_Of_Transactions_Enqueued="14471" No_Of_Transactions_Dequeued="14471" Avg_Queue_Length="14.667510" Max_Queue_Length="606" STDev_Queue_Length="360.773782" Avg_Transaction_Waiting_Time="101821" Max_Transaction_Waiting_Time="245477"/>
			<SSDDevice.TSU.GC_Write_TR_Queue Name="GC_Write_TR_Queue@0@1" No_Of_Transactions_Enqueued="14104" No_Of_Transactions_Dequeued="14104" Avg_Queue_Length="13.200166" Max_Queue_Length="476" STDev_Queue_Length="287.692152" Avg_Transaction_Waiting_Time="94019" Max_Transaction_Waiting_Time="216244"/>
			<SSDDevice.TSU.GC_Write_TR_Queue Name="GC_Write_TR_Queue@0@2" No_Of_Transactions_Enqueued="14048" No_Of_Transactions_Dequeued="14048" Avg_Queue_Length="12.995332" Max_Queue_Length="406" STDev_Queue_Length="261.527522" Avg_Transaction_Waiting_Time="92929" Max_Transaction_Waiting_Time="196511"/>
			<SSDDevice.TSU.GC_Write_TR_Queue Name="GC_Write_TR_Queue@0@3" No_Of_Transactions_Enqueued="14304" No_Of_Transactions_Dequeued="14304" Avg_Queue_Length="14.048895" Max_Queue_Length="566" STDev_Queue_Length="333.939343" Avg_Transaction_Waiting_Time="98665" Max_Transaction_Waiting_Time="227804"/>
			<SSDDevice.TSU.GC_Write_TR_Queue Name="GC_Write_TR_Queue@1@0" No_Of_Transactions_Enqueued="14078" No_Of_Transactions_Dequeued="14078" Avg_Queue_Length="13.278207" Max_Queue_Length="504" STDev_Queue_Length="297.800270" Avg_Transaction_Waiting_Time="94750" Max_Transaction_Waiting_Time="222573"/>
			<SSDDevice.TSU.GC_Write_TR_Queue Name="GC_Write_TR_Queue@1@1" No_Of_Transactions_Enqueued="14075" No_Of_Transactions_Dequeued="14075" Avg_Queue_Length="13.763898" Max_Queue_Length="735" STDev_Queue_Length="372.898311" Avg_Transaction_Waiting_Time="98236" Max_Transaction_Waiting_Time="237153"/>
			<SSDDevice.TSU.GC_Write_TR_Queue Name="GC_Write_TR_Queue@1@2" No_Of_Transactions_Enqueued="13893" No_Of_Transactions_Dequeued="13893" Avg_Queue_Length="13.499285" Max_Queue_Length="566" STDev_Queue_Length="320.875334" Avg_Transaction_Waiting_Time="97610" Max_Transaction_Waiting_Time="231575"/>
			<SSDDevice.TSU.GC_Write_TR_Queue Name="GC_Write_TR_Queue@1@3" No_Of_Transactions_Enqueued="14466" No_Of_Transactions_Dequeued="14466" Avg_Queue_Length="13.777862" Max_Queue_Length="615" STDev_Queue_Length="341.402986" Avg_Transaction_Waiting_Time="95678" Max_Transaction_Waiting_Time="223428"/>
			<SSDDevice.TSU.GC_Write_TR_Queue Name="GC_Write_TR_Queue@2@0" No_Of_Transactions_Enqueued="14086" No_Of_Transactions_Dequeued="14086" Avg_Queue_Length="13.997303" Max_Queue_Length="780" STDev_Queue_Length="390.673460" Avg_Transaction_Waiting_Time="99824" Max_Transaction_Waiting_Time="276223"/>
			<SSDDevice.TSU.GC_Write_TR_Queue Name="GC_Write_TR_Queue@2@1" No_Of_Transactions_Enqueued="14488" No_Of_Transactions_Dequeued="14488" Avg_Queue_Length="14.036233" Max_Queue_Length="564" STDev_Queue_Length="333.047475" Avg_Transaction_Waiting_Time="97324" Max_Transaction_Waiting_Time="246730"/>
			<SSDDevice.TSU.GC_Write_TR_Queue Name="GC_Write_TR_Queue@2@2" No_Of_Transactions_Enqueued="13727" No_Of_Transactions_Dequeued="13727" Avg_Queue_Length="13.489807" Max_Queue_Length="557" STDev_Queue_Length="318.085975" Avg_Transaction_Waiting_Time="98721" Max_Transaction_Waiting_Time="234751"/>
			<SSDDevice.TSU.GC_Write_TR_Queue Name="GC_Write_TR_Queue@2@3" No_Of_Transactions_Enqueued="13722" No_Of_Transactions_Dequeued="13722" Avg_Queue_Length="13.590719" Max_Queue_Length="602" STDev_Queue_Length="333.181397" Avg_Transaction_Waiting_Time="99496" Max_Transaction_Waiting_Time="239617"/>
			<SSDDevice.TSU.GC_Write_TR_Queue Name="GC_Write_TR_Queue@3@0" No_Of_Transactions_Enqueued="14111" No_Of_Transactions_Dequeued="14111" Avg_Queue_Length="13.376988" Max_Queue_Length="409" STDev_Queue_Length="270.203300" Avg_Transaction_Waiting_Time="95231" Max_Transaction_Waiting_Time="231764"/>
			<SSDDevice.TSU.GC_Write_TR_Queue Name="GC_Write_TR_Queue@3@1" No_Of_Transactions_Enqueued="14506" No_Of_Transactions_Dequeued="14506" Avg_Queue_Length="13.326392" Max_Queue_Length="409" STDev_Queue_Length="269.181595" Avg_Transaction_Waiting_Time="92288" Max_Transaction_Waiting_Time="211940"/>
			<SSDDevice.TSU.GC_Write_TR_Queue Name="GC_Write_TR_Queue@3@2" No_Of_Transactions_Enqueued="14081" No_Of_Transactions_Dequeued="14081" Avg_Queue_Length="13.177777" Max_Queue_Length="733" STDev_Queue_Length="356.532431" Avg_Transaction_Waiting_Time="94013" Max_Transaction_Waiting_Time="226979"/>
			<SSDDevice.TSU.GC_Write_TR_Queue Name="GC_Write_TR_Queue@3@3" No_Of_Transactions_Enqueued="13707" No_Of_Transactions_Dequeued="13707" Avg_Queue_Length="13.065007" Max_Queue_Length="809" STDev_Queue_Length="371.378123" Avg_Transaction_Waiting_Time="95752" Max_Transaction_Waiting_Time="241631"/>
			<SSDDevice.TSU.GC_Write_TR_Queue Name="GC_Write_TR_Queue@4@0" No_Of_Transactions_Enqueued="46661" No_Of_Transactions_Dequeued="46661" Avg_Queue_Length="39.955318" Max_Queue_Length="383" STDev_Queue_Length="780.924687" Avg_Transaction_Waiting_Time="86020" Max_Transaction_Waiting_Time="213659"/>
			<SSDDevice.TSU.GC_Write_TR_Queue Name="GC_Write_TR_Queue@4@1" No_Of_Transactions_Enqueued="45681" No_Of_Transactions_Dequeued="45681" Avg_Queue_Length="39.715236" Max_Queue_Length="552" STDev_Queue_Length="932.255120" Avg_Transaction_Waiting_Time="87337" Max_Transaction_Waiting_Time="233826"/>
			<SSDDevice.TSU.GC_Write_TR_Queue Name="GC_Write_TR_Queue@4@2" No_Of_Transactions_Enqueued="46372" No_Of_Transactions_Dequeued="46372" Avg_Queue_Length="41.009900" Max_Queue_Length="585" STDev_Queue_Length="991.052185" Avg_Transaction_Waiting_Time="88841" Max_Transaction_Waiting_Time="226237"/>
			<SSDDevice.TSU.GC_Write_TR_Queue Name="GC_Write_TR_Queue@4@3" No_Of_Transactions_Enqueued="46128" No_Of_Transactions_Dequeued="46128" Avg_Queue_Length="41.508888" Max_Queue_Length="738" STDev_Queue_Length="1126.875143" Avg_Transaction_Waiting_Time="90397" Max_Transaction_Waiting_Time="238430"/>
			<SSDDevice.TSU.GC_Write_TR_Queue Name="GC_Write_TR_Queue@5@0" No_Of_Transactions_Enqueued="45799" No_Of_Transactions_Dequeued="45799" Avg_Queue_Length="39.876605" Max_Queue_Length="546" STDev_Queue_Length="930.932199" Avg_Transaction_Waiting_Time="87466" Max_Transaction_Waiting_Time="219882"/>
			<SSDDevice.TSU.GC_Write_TR_Queue Name="GC_Write_TR_Queue@5@1" No_Of_Transactions_Enqueued="46337" No_Of_Transactions_Dequeued="46337" Avg_Queue_Length="40.786033" Max_Queue_Length="546" STDev_Queue_Length="952.162959" Avg_Transaction_Waiting_Time="88422" Max_Transaction_Waiting_Time="209048"/>
			<SSDDevice.TSU.GC_Write_TR_Queue Name="GC_Write_TR_Queue@5@2" No_Of_Transactions_Enqueued="46073" No_Of_Transactions_Dequeued="46073" Avg_Queue_Length="41.551087" Max_Queue_Length="524" STDev_Queue_Length="950.243271" Avg_Transaction_Waiting_Time="90597" Max_Transaction_Waiting_Time="254621"/>
			<SSDDevice.TSU.GC_Write_TR_Queue Name="GC_Write_TR_Queue@5@3" No_Of_Transactions_Enqueued="45728" No_Of_Transactions_Dequeued="45728" Avg_Queue_Length="40.112467" Max_Queue_Length="548" STDev_Queue_Length="938.155101" Avg_Transaction_Waiting_Time="88120" Max_Transaction_Waiting_Time="218215"/>
			<SSDDevice.TSU.GC_Write_TR_Queue Name="GC_Write_TR_Queue@6@0" No_Of_Transactions_Enqueued="46391" No_Of_Transactions_Dequeued="46391" Avg_Queue_Length="39.896583" Max_Queue_Length="396" STDev_Queue_Length="792.933797" Avg_Transaction_Waiting_Time="86393" Max_Transaction_Waiting_Time="217674"/>
			<SSDDevice.TSU.GC_Write_TR_Queue Name="GC_Write_TR_Queue@6@1" No_Of_Transactions_Enqueued="46352" No_Of_Transactions_Dequeued="46352" Avg_Queue_Length="40.709030" Max_Queue_Length="489" STDev_Queue_Length="899.295505" Avg_Transaction_Waiting_Time="88227" Max_Transaction_Waiting_Time="232398"/>
			<SSDDevice.TSU.GC_Write_TR_Queue Name="GC_Write_TR_Queue@6@2" No_Of_Transactions_Enqueued="46204" No_Of_Transactions_Dequeued="46204" Avg_Queue_Length="39.930546" Max_Queue_Length="557" STDev_Queue_Length="941.551908" Avg_Transaction_Waiting_Time="86817" Max_Transaction_Waiting_Time="207255"/>
			<SSDDevice.TSU.GC_Write_TR_Queue Name="GC_Write_TR_Queue@6@3" No_Of_Transactions_Enqueued="45866" No_Of_Transactions_Dequeued="45866" Avg_Queue_Length="38.978043" Max_Queue_Length="529" STDev_Queue_Length="895.651441" Avg_Transaction_Waiting_Time="85371" Max_Transaction_Waiting_Time="211692"/>
			<SSDDevice.TSU.GC_Write_TR_Queue Name="GC_Write_TR_Queue@7@0" No_Of_Transactions_Enqueued="46125" No_Of_Transactions_Dequeued="46125" Avg_Queue_Length="39.296108" Max_Queue_Length="458" STDev_Queue_Length="840.059103" Avg_Transaction_Waiting_Time="85584" Max_Transaction_Waiting_Time="212045"/>
			<SSDDevice.TSU.GC_Write_TR_Queue Name="GC_Write_TR_Queue@7@1" No_Of_Transactions_Enqueued="46159" No_Of_Transactions_Dequeued="46159" Avg_Queue_Length="40.881650" Max_Queue_Length="542" STDev_Queue_Length="950.886398" Avg_Transaction_Waiting_Time="88972" Max_Transaction_Waiting_Time="225307"/>
			<SSDDevice.TSU.GC_Write_TR_Queue Name="GC_Write_TR_Queue@7@2" No_Of_Transactions_Enqueued="45865" No_Of_Transactions_Dequeued="45865" Avg_Queue_Length="39.325263" Max_Queue_Length="520" STDev_Queue_Length="895.895266" Avg_Transaction_Waiting_Time="86133" Max_Transaction_Waiting_Time="248404"/>
			<SSDDevice.TSU.GC_Write_TR_Queue Name="GC_Write_TR_Queue@7@3" No_Of_Transactions_Enqueued="46545" No_Of_Transactions_Dequeued="46545" Avg_Queue_Length="39.633538" Max_Queue_Length="562" STDev_Queue_Length="938.741580" Avg_Transaction_Waiting_Time="85540" Max_Transaction_Waiting_Time="216938"/>
			<SSDDevice.TSU.GC_Erase_TR_Queue Name="GC_Erase_TR_Queue@0@0" No_Of_Transactions_Enqueued="72" No_Of_Transactions_Dequeued="72" Avg_Queue_Length="0.168659" Max_Queue_Length="4" STDev_Queue_Length="0.305082" Avg_Transaction_Waiting_Time="235320" Max_Transaction_Waiting_Time="493869"/>
			<SSDDevice.TSU.GC_Erase_TR_Queue Name="GC_Erase_TR_Queue@0@1" No_Of_Transactions_Enqueued="72" No_Of_Transactions_Dequeued="72" Avg_Queue_Length="0.133990" Max_Queue_Length="3" STDev_Queue_Length="0.211642" Avg_Transaction_Waiting_Time="186948" Max_Transaction_Waiting_Time="323173"/>
			<SSDDevice.TSU.GC_Erase_TR_Queue Name="GC_Erase_TR_Queue@0@2" No_Of_Transactions_Enqueued="73" No_Of_Transactions_Dequeued="73" Avg_Queue_Length="0.136227" Max_Queue_Length="3" STDev_Queue_Length="0.216747" Avg_Transaction_Waiting_Time="187465" Max_Transaction_Waiting_Time="393206"/>
			<SSDDevice.TSU.GC_Erase_TR_Queue Name="GC_Erase_TR_Queue@0@3" No_Of_Transactions_Enqueued="72" No_Of_Transactions_Dequeued="72" Avg_Queue_Length="0.169607" Max_Queue_Length="4" STDev_Queue_Length="0.306514" Avg_Transaction_Waiting_Time="236642" Max_Transaction_Waiting_Time="546370"/>
			<SSDDevice.TSU.GC_Erase_TR_Queue Name="GC_Erase_TR_Queue@1@0" No_Of_Transactions_Enqueued="72" No_Of_Transactions_Dequeued="72" Avg_Queue_Length="0.141859" Max_Queue_Length="4" STDev_Queue_Length="0.261729" Avg_Transaction_Waiting_Time="197927" Max_Transaction_Waiting_Time="432431"/>
			<SSDDevice.TSU.GC_Erase_TR_Queue Name="GC_Erase_TR_Queue@1@1" No_Of_Transactions_Enqueued="72" No_Of_Transactions_Dequeued="72" Avg_Queue_Length="0.151157" Max_Queue_Length="4" STDev_Queue_Length="0.276184" Avg_Transaction_Waiting_Time="210900" Max_Transaction_Waiting_Time="445208"/>
			<SSDDevice.TSU.GC_Erase_TR_Queue Name="GC_Erase_TR_Queue@1@2" No_Of_Transactions_Enqueued="72" No_Of_Transactions_Dequeued="72" Avg_Queue_Length="0.159040" Max_Queue_Length="4" STDev_Queue_Length="0.288488" Avg_Transaction_Waiting_Time="221898" Max_Transaction_Waiting_Time="543696"/>
			<SSDDevice.TSU.GC_Erase_TR_Queue Name="GC_Erase_TR_Queue@1@3" No_Of_Transactions_Enqueued="72" No_Of_Transactions_Dequeued="72" Avg_Queue_Length="0.143552" Max_Queue_Length="3" STDev_Queue_Length="0.223563" Avg_Transaction_Waiting_Time="200289" Max_Transaction_Waiting_Time="373592"/>
			<SSDDevice.TSU.GC_Erase_TR_Queue Name="GC_Erase_TR_Queue@2@0" No_Of_Transactions_Enqueued="72" No_Of_Transactions_Dequeued="72" Avg_Queue_Length="0.156525" Max_Queue_Length="4" STDev_Queue_Length="0.283953" Avg_Transaction_Waiting_Time="218390" Max_Transaction_Waiting_Time="419247"/>
			<SSDDevice.TSU.GC_Erase_TR_Queue Name="GC_Erase_TR_Queue@2@1" No_Of_Transactions_Enqueued="72" No_Of_Transactions_Dequeued="72" Avg_Queue_Length="0.162188" Max_Queue_Length="4" STDev_Queue_Length="0.295623" Avg_Transaction_Waiting_Time="226291" Max_Transaction_Waiting_Time="542889"/>
			<SSDDevice.TSU.GC_Erase_TR_Queue Name="GC_Erase_TR_Queue@2@2" No_Of_Transactions_Enqueued="72" No_Of_Transactions_Dequeued="72" Avg_Queue_Length="0.164885" Max_Queue_Length="4" STDev_Queue_Length="0.300178" Avg_Transaction_Waiting_Time="230053" Max_Transaction_Waiting_Time="471329"/>
			<SSDDevice.TSU.GC_Erase_TR_Queue Name="GC_Erase_TR_Queue@2@3" No_Of_Transactions_Enqueued="72" No_Of_Transactions_Dequeued="72" Avg_Queue_Length="0.150490" Max_Queue_Length="4" STDev_Queue_Length="0.273958" Avg_Transaction_Waiting_Time="209970" Max_Transaction_Waiting_Time="414253"/>
			<SSDDevice.TSU.GC_Erase_TR_Queue Name="GC_Erase_TR_Queue@3@0" No_Of_Transactions_Enqueued="72" No_Of_Transactions_Dequeued="72" Avg_Queue_Length="0.153100" Max_Queue_Length="3" STDev_Queue_Length="0.236475" Avg_Transaction_Waiting_Time="213611" Max_Transaction_Waiting_Time="466316"/>
			<SSDDevice.TSU.GC_Erase_TR_Queue Name="GC_Erase_TR_Queue@3@1" No_Of_Transactions_Enqueued="72" No_Of_Transactions_Dequeued="72" Avg_Queue_Length="0.135219" Max_Queue_Length="2" STDev_Queue_Length="0.173592" Avg_Transaction_Waiting_Time="188662" Max_Transaction_Waiting_Time="367731"/>
			<SSDDevice.TSU.GC_Erase_TR_Queue Name="GC_Erase_TR_Queue@3@2" No_Of_Transactions_Enqueued="72" No_Of_Transactions_Dequeued="72" Avg_Queue_Length="0.143481" Max_Queue_Length="4" STDev_Queue_Length="0.266299" Avg_Transaction_Waiting_Time="200191" Max_Transaction_Waiting_Time="450933"/>
			<SSDDevice.TSU.GC_Erase_TR_Queue Name="GC_Erase_TR_Queue@3@3" No_Of_Transactions_Enqueued="73" No_Of_Transactions_Dequeued="73" Avg_Queue_Length="0.142678" Max_Queue_Length="4" STDev_Queue_Length="0.261900" Avg_Transaction_Waiting_Time="196343" Max_Transaction_Waiting_Time="462326"/>
			<SSDDevice.TSU.GC_Erase_TR_Queue Name="GC_Erase_TR_Queue@4@0" No_Of_Transactions_Enqueued="250" No_Of_Transactions_Dequeued="250" Avg_Queue_Length="0.463289" Max_Queue_Length="3" STDev_Queue_Length="0.739007" Avg_Transaction_Waiting_Time="186162" Max_Transaction_Waiting_Time="336435"/>
			<SSDDevice.TSU.GC_Erase_TR_Queue Name="GC_Erase_TR_Queue@4@1" No_Of_Transactions_Enqueued="248" No_Of_Transactions_Dequeued="248" Avg_Queue_Length="0.472130" Max_Queue_Length="3" STDev_Queue_Length="0.742015" Avg_Transaction_Waiting_Time="191245" Max_Transaction_Waiting_Time="404326"/>
			<SSDDevice.TSU.GC_Erase_TR_Queue Name="GC_Erase_TR_Queue@4@2" No_Of_Transactions_Enqueued="250" No_Of_Transactions_Dequeued="250" Avg_Queue_Length="0.487541" Max_Queue_Length="3" STDev_Queue_Length="0.751836" Avg_Transaction_Waiting_Time="195908" Max_Transaction_Waiting_Time="353593"/>
			<SSDDevice.TSU.GC_Erase_TR_Queue Name="GC_Erase_TR_Queue@4@3" No_Of_Transactions_Enqueued="249" No_Of_Transactions_Dequeued="249" Avg_Queue_Length="0.537253" Max_Queue_Length="4" STDev_Queue_Length="0.974066" Avg_Transaction_Waiting_Time="216751" Max_Transaction_Waiting_Time="498687"/>
			<SSDDevice.TSU.GC_Erase_TR_Queue Name="GC_Erase_TR_Queue@5@0" No_Of_Transactions_Enqueued="248" No_Of_Transactions_Dequeued="248" Avg_Queue_Length="0.518214" Max_Queue_Length="4" STDev_Queue_Length="0.945115" Avg_Transaction_Waiting_Time="209912" Max_Transaction_Waiting_Time="533382"/>
			<SSDDevice.TSU.GC_Erase_TR_Queue Name="GC_Erase_TR_Queue@5@1" No_Of_Transactions_Enqueued="250" No_Of_Transactions_Dequeued="250" Avg_Queue_Length="0.513953" Max_Queue_Length="4" STDev_Queue_Length="0.940769" Avg_Transaction_Waiting_Time="206521" Max_Transaction_Waiting_Time="546997"/>
			<SSDDevice.TSU.GC_Erase_TR_Queue Name="GC_Erase_TR_Queue@5@2" No_Of_Transactions_Enqueued="249" No_Of_Transactions_Dequeued="249" Avg_Queue_Length="0.538016" Max_Queue_Length="4" STDev_Queue_Length="0.981267" Avg_Transaction_Waiting_Time="217058" Max_Transaction_Waiting_Time="504115"/>
			<SSDDevice.TSU.GC_Erase_TR_Queue Name="GC_Erase_TR_Queue@5@3" No_Of_Transactions_Enqueued="247" No_Of_Transactions_Dequeued="247" Avg_Queue_Length="0.508597" Max_Queue_Length="4" STDev_Queue_Length="0.930863" Avg_Transaction_Waiting_Time="206851" Max_Transaction_Waiting_Time="492200"/>
			<SSDDevice.TSU.GC_Erase_TR_Queue Name="GC_Erase_TR_Queue@6@0" No_Of_Transactions_Enqueued="250" No_Of_Transactions_Dequeued="250" Avg_Queue_Length="0.469186" Max_Queue_Length="3" STDev_Queue_Length="0.744252" Avg_Transaction_Waiting_Time="188532" Max_Transaction_Waiting_Time="416533"/>
			<SSDDevice.TSU.GC_Erase_TR_Queue Name="GC_Erase_TR_Queue@6@1" No_Of_Transactions_Enqueued="249" No_Of_Transactions_Dequeued="249" Avg_Queue_Length="0.485015" Max_Queue_Length="3" STDev_Queue_Length="0.748987" Avg_Transaction_Waiting_Time="195676" Max_Transaction_Waiting_Time="420567"/>
			<SSDDevice.TSU.GC_Erase_TR_Queue Name="GC_Erase_TR_Queue@6@2" No_Of_Transactions_Enqueued="249" No_Of_Transactions_Dequeued="249" Avg_Queue_Length="0.481995" Max_Queue_Length="3" STDev_Queue_Length="0.748011" Avg_Transaction_Waiting_Time="194457" Max_Transaction_Waiting_Time="457572"/>
			<SSDDevice.TSU.GC_Erase_TR_Queue Name="GC_Erase_TR_Queue@6@3" No_Of_Transactions_Enqueued="247" No_Of_Transactions_Dequeued="247" Avg_Queue_Length="0.451417" Max_Queue_Length="3" STDev_Queue_Length="0.717502" Avg_Transaction_Waiting_Time="183595" Max_Transaction_Waiting_Time="410513"/>
			<SSDDevice.TSU.GC_Erase_TR_Queue Name="GC_Erase_TR_Queue@7@0" No_Of_Transactions_Enqueued="250" No_Of_Transactions_Dequeued="250" Avg_Queue_Length="0.473113" Max_Queue_Length="3" STDev_Queue_Length="0.740713" Avg_Transaction_Waiting_Time="190110" Max_Transaction_Waiting_Time="448375"/>
			<SSDDevice.TSU.GC_Erase_TR_Queue Name="GC_Erase_TR_Queue@7@1" No_Of_Transactions_Enqueued="249" No_Of_Transactions_Dequeued="249" Avg_Queue_Length="0.509298" Max_Queue_Length="4" STDev_Queue_Length="0.932036" Avg_Transaction_Waiting_Time="205472" Max_Transaction_Waiting_Time="446100"/>
			<SSDDevice.TSU.GC_Erase_TR_Queue Name="GC_Erase_TR_Queue@7@2" No_Of_Transactions_Enqueued="249" No_Of_Transactions_Dequeued="249" Avg_Queue_Length="0.468001" Max_Queue_Length="4" STDev_Queue_Length="0.870097" Avg_Transaction_Waiting_Time="188811" Max_Transaction_Waiting_Time="489890"/>
			<SSDDevice.TSU.GC_Erase_TR_Queue Name="GC_Erase_TR_Queue@7@3" No_Of_Transactions_Enqueued="251" No_Of_Transactions_Dequeued="251" Avg_Queue_Length="0.463203" Max_Queue_Length="4" STDev_Queue_Length="0.864100" Avg_Transaction_Waiting_Time="185386" Max_Transaction_Waiting_Time="458811"/>
		</SSDDevice.TSU>
		<SSDDevice.FlashChips ID="@0@0" Fraction_of_Time_in_Execution="0.214429" Fraction_of_Time_in_DataXfer="0.009614" Fraction_of_Time_in_DataXfer_and_Execution="0.001207" Fraction_of_Time_Idle="0.989179"/>
		<SSDDevice.FlashChips ID="@0@1" Fraction_of_Time_in_Execution="0.230145" Fraction_of_Time_in_DataXfer="0.009424" Fraction_of_Time_in_DataXfer_and_Execution="0.000636" Fraction_of_Time_Idle="0.989940"/>
		<SSDDevice.FlashChips ID="@0@2" Fraction_of_Time_in_Execution="0.233089" Fraction_of_Time_in_DataXfer="0.009397" Fraction_of_Time_in_DataXfer_and_Execution="0.000533" Fraction_of_Time_Idle="0.990070"/>
		<SSDDevice.FlashChips ID="@0@3" Fraction_of_Time_in_Execution="0.221816" Fraction_of_Time_in_DataXfer="0.009524" Fraction_of_Time_in_DataXfer_and_Execution="0.000827" Fraction_of_Time_Idle="0.989649"/>
		<SSDDevice.FlashChips ID="@1@0" Fraction_of_Time_in_Execution="0.227640" Fraction_of_Time_in_DataXfer="0.009401" Fraction_of_Time_in_DataXfer_and_Execution="0.000734" Fraction_of_Time_Idle="0.989865"/>
		<SSDDevice.FlashChips ID="@1@1" Fraction_of_Time_in_Execution="0.227026" Fraction_of_Time_in_DataXfer="0.009416" Fraction_of_Time_in_DataXfer_and_Execution="0.000594" Fraction_of_Time_Idle="0.989989"/>
		<SSDDevice.FlashChips ID="@1@2" Fraction_of_Time_in_Execution="0.221178" Fraction_of_Time_in_DataXfer="0.009318" Fraction_of_Time_in_DataXfer_and_Execution="0.000632" Fraction_of_Time_Idle="0.990050"/>
		<SSDDevice.FlashChips ID="@1@3" Fraction_of_Time_in_Execution="0.230159" Fraction_of_Time_in_DataXfer="0.009608" Fraction_of_Time_in_DataXfer_and_Execution="0.000495" Fraction_of_Time_Idle="0.989897"/>
		<SSDDevice.FlashChips ID="@2@0" Fraction_of_Time_in_Execution="0.221855" Fraction_of_Time_in_DataXfer="0.009412" Fraction_of_Time_in_DataXfer_and_Execution="0.000906" Fraction_of_Time_Idle="0.989682"/>
		<SSDDevice.FlashChips ID="@2@1" Fraction_of_Time_in_Execution="0.227495" Fraction_of_Time_in_DataXfer="0.009617" Fraction_of_Time_in_DataXfer_and_Execution="0.000614" Fraction_of_Time_Idle="0.989769"/>
		<SSDDevice.FlashChips ID="@2@2" Fraction_of_Time_in_Execution="0.223404" Fraction_of_Time_in_DataXfer="0.009233" Fraction_of_Time_in_DataXfer_and_Execution="0.000722" Fraction_of_Time_Idle="0.990045"/>
		<SSDDevice.FlashChips ID="@2@3" Fraction_of_Time_in_Execution="0.220228" Fraction_of_Time_in_DataXfer="0.009240" Fraction_of_Time_in_DataXfer_and_Execution="0.000695" Fraction_of_Time_Idle="0.990065"/>
		<SSDDevice.FlashChips ID="@3@0" Fraction_of_Time_in_Execution="0.229561" Fraction_of_Time_in_DataXfer="0.009415" Fraction_of_Time_in_DataXfer_and_Execution="0.000647" Fraction_of_Time_Idle="0.989937"/>
		<SSDDevice.FlashChips ID="@3@1" Fraction_of_Time_in_Execution="0.241082" Fraction_of_Time_in_DataXfer="0.009625" Fraction_of_Time_in_DataXfer_and_Execution="0.000321" Fraction_of_Time_Idle="0.990054"/>
		<SSDDevice.FlashChips ID="@3@2" Fraction_of_Time_in_Execution="0.232709" Fraction_of_Time_in_DataXfer="0.009405" Fraction_of_Time_in_DataXfer_and_Execution="0.000596" Fraction_of_Time_Idle="0.989999"/>
		<SSDDevice.FlashChips ID="@3@3" Fraction_of_Time_in_Execution="0.226167" Fraction_of_Time_in_DataXfer="0.009232" Fraction_of_Time_in_DataXfer_and_Execution="0.000661" Fraction_of_Time_Idle="0.990107"/>
		<SSDDevice.FlashChips ID="@4@0" Fraction_of_Time_in_Execution="0.670542" Fraction_of_Time_in_DataXfer="0.031261" Fraction_of_Time_in_DataXfer_and_Execution="0.003144" Fraction_of_Time_Idle="0.965596"/>
		<SSDDevice.FlashChips ID="@4@1" Fraction_of_Time_in_Execution="0.658260" Fraction_of_Time_in_DataXfer="0.030719" Fraction_of_Time_in_DataXfer_and_Execution="0.002869" Fraction_of_Time_Idle="0.966412"/>
		<SSDDevice.FlashChips ID="@4@2" Fraction_of_Time_in_Execution="0.649479" Fraction_of_Time_in_DataXfer="0.031151" Fraction_of_Time_in_DataXfer_and_Execution="0.003925" Fraction_of_Time_Idle="0.964924"/>
		<SSDDevice.FlashChips ID="@4@3" Fraction_of_Time_in_Execution="0.628413" Fraction_of_Time_in_DataXfer="0.031019" Fraction_of_Time_in_DataXfer_and_Execution="0.003772" Fraction_of_Time_Idle="0.965209"/>
		<SSDDevice.FlashChips ID="@5@0" Fraction_of_Time_in_Execution="0.647248" Fraction_of_Time_in_DataXfer="0.030819" Fraction_of_Time_in_DataXfer_and_Execution="0.003758" Fraction_of_Time_Idle="0.965423"/>
		<SSDDevice.FlashChips ID="@5@1" Fraction_of_Time_in_Execution="0.642531" Fraction_of_Time_in_DataXfer="0.031097" Fraction_of_Time_in_DataXfer_and_Execution="0.004123" Fraction_of_Time_Idle="0.964780"/>
		<SSDDevice.FlashChips ID="@5@2" Fraction_of_Time_in_Execution="0.646796" Fraction_of_Time_in_DataXfer="0.030981" Fraction_of_Time_in_DataXfer_and_Execution="0.003658" Fraction_of_Time_Idle="0.965361"/>
		<SSDDevice.FlashChips ID="@5@3" Fraction_of_Time_in_Execution="0.645631" Fraction_of_Time_in_DataXfer="0.030765" Fraction_of_Time_in_DataXfer_and_Execution="0.003736" Fraction_of_Time_Idle="0.965499"/>
		<SSDDevice.FlashChips ID="@6@0" Fraction_of_Time_in_Execution="0.668185" Fraction_of_Time_in_DataXfer="0.031123" Fraction_of_Time_in_DataXfer_and_Execution="0.003185" Fraction_of_Time_Idle="0.965692"/>
		<SSDDevice.FlashChips ID="@6@1" Fraction_of_Time_in_Execution="0.643725" Fraction_of_Time_in_DataXfer="0.031101" Fraction_of_Time_in_DataXfer_and_Execution="0.003869" Fraction_of_Time_Idle="0.965029"/>
		<SSDDevice.FlashChips ID="@6@2" Fraction_of_Time_in_Execution="0.652504" Fraction_of_Time_in_DataXfer="0.031017" Fraction_of_Time_in_DataXfer_and_Execution="0.004013" Fraction_of_Time_Idle="0.964971"/>
		<SSDDevice.FlashChips ID="@6@3" Fraction_of_Time_in_Execution="0.658994" Fraction_of_Time_in_DataXfer="0.030792" Fraction_of_Time_in_DataXfer_and_Execution="0.003423" Fraction_of_Time_Idle="0.965786"/>
		<SSDDevice.FlashChips ID="@7@0" Fraction_of_Time_in_Execution="0.663726" Fraction_of_Time_in_DataXfer="0.030973" Fraction_of_Time_in_DataXfer_and_Execution="0.003412" Fraction_of_Time_Idle="0.965614"/>
		<SSDDevice.FlashChips ID="@7@1" Fraction_of_Time_in_Execution="0.653368" Fraction_of_Time_in_DataXfer="0.030977" Fraction_of_Time_in_DataXfer_and_Execution="0.003756" Fraction_of_Time_Idle="0.965267"/>
		<SSDDevice.FlashChips ID="@7@2" Fraction_of_Time_in_Execution="0.661949" Fraction_of_Time_in_DataXfer="0.030786" Fraction_of_Time_in_DataXfer_and_Execution="0.003307" Fraction_of_Time_Idle="0.965907"/>
		<SSDDevice.FlashChips ID="@7@3" Fraction_of_Time_in_Execution="0.660755" Fraction_of_Time_in_DataXfer="0.031243" Fraction_of_Time_in_DataXfer_and_Execution="0.003540" Fraction_of_Time_Idle="0.965217"/>
	</SSDDevice>
</MQSim_Results>
